compress.v
/*
 * 模块名称：compress
 *
 * 功能描述：
 *   本模块实现SHA-256算法的压缩函数部分，采用32级流水线结构。
 *   输出最终的哈希值。
 *
 * 主要特点：
 *   1. 32级流水线处理64个Wt
 *   2. 完全同步设计，与扩展模块时钟对齐
 *   3. 支持连续块处理，保持高吞吐量
 */

module compress (
    input              clk,
    input              rst_n,
    input      [ 31:0] Wt_in,          // 来自消息扩展的Wt (Wt0-Wt63)
    input              Wt_valid,       // Wt输入有效信号
    input      [255:0] hash_in,        // 初始哈希值或前一块的哈希
    output reg [255:0] hash_out,       // 压缩后的哈希值
    output reg         hash_out_valid  // 哈希输出有效信号
);

  // =============================================
  // 内部寄存器定义
  // =============================================
  reg [ 31:0] K                                        [0:63];  // SHA-256常量

  // 32级流水线寄存器
  reg [ 31:0] a                                        [0:31];  // a工作变量流水线
  reg [ 31:0] b                                        [0:31];  // b工作变量流水线
  reg [ 31:0] c                                        [0:31];  // c工作变量流水线
  reg [ 31:0] d                                        [0:31];  // d工作变量流水线
  reg [ 31:0] e                                        [0:31];  // e工作变量流水线
  reg [ 31:0] f                                        [0:31];  // f工作变量流水线
  reg [ 31:0] g                                        [0:31];  // g工作变量流水线
  reg [ 31:0] h                                        [0:31];  // h工作变量流水线

  reg [255:0] hash_reg;  // 输入哈希值寄存器
  reg [  5:0] wt_counter;  // Wt计数器 (0-63)
  reg         zip_active;  // 压缩过程激活标志
  reg         output_stage;  // 输出阶段标志

  // =============================================
  // Σ函数定义
  // =============================================
  function [31:0] SIGMA0;
    input [31:0] x;
    SIGMA0 = {x[1:0], x[31:2]} ^ {x[12:0], x[31:13]} ^ {x[21:0], x[31:22]};
  endfunction

  function [31:0] SIGMA1;
    input [31:0] x;
    SIGMA1 = {x[5:0], x[31:6]} ^ {x[10:0], x[31:11]} ^ {x[24:0], x[31:25]};
  endfunction

  // =============================================
  // 选择函数和多数函数
  // =============================================
  function [31:0] Ch;
    input [31:0] x, y, z;
    Ch = (x & y) ^ (~x & z);
  endfunction

  function [31:0] Maj;
    input [31:0] x, y, z;
    Maj = (x & y) ^ (x & z) ^ (y & z);
  endfunction

  // =============================================
  // 常量初始化
  // =============================================
  initial begin
    K[0]  = 32'h428a2f98;
    K[1]  = 32'h71374491;
    K[2]  = 32'hb5c0fbcf;
    K[3]  = 32'he9b5dba5;
    K[4]  = 32'h3956c25b;
    K[5]  = 32'h59f111f1;
    K[6]  = 32'h923f82a4;
    K[7]  = 32'hab1c5ed5;
    K[8]  = 32'hd807aa98;
    K[9]  = 32'h12835b01;
    K[10] = 32'h243185be;
    K[11] = 32'h550c7dc3;
    K[12] = 32'h72be5d74;
    K[13] = 32'h80deb1fe;
    K[14] = 32'h9bdc06a7;
    K[15] = 32'hc19bf174;
    K[16] = 32'he49b69c1;
    K[17] = 32'hefbe4786;
    K[18] = 32'h0fc19dc6;
    K[19] = 32'h240ca1cc;
    K[20] = 32'h2de92c6f;
    K[21] = 32'h4a7484aa;
    K[22] = 32'h5cb0a9dc;
    K[23] = 32'h76f988da;
    K[24] = 32'h983e5152;
    K[25] = 32'ha831c66d;
    K[26] = 32'hb00327c8;
    K[27] = 32'hbf597fc7;
    K[28] = 32'hc6e00bf3;
    K[29] = 32'hd5a79147;
    K[30] = 32'h06ca6351;
    K[31] = 32'h14292967;
    K[32] = 32'h27b70a85;
    K[33] = 32'h2e1b2138;
    K[34] = 32'h4d2c6dfc;
    K[35] = 32'h53380d13;
    K[36] = 32'h650a7354;
    K[37] = 32'h766a0abb;
    K[38] = 32'h81c2c92e;
    K[39] = 32'h92722c85;
    K[40] = 32'ha2bfe8a1;
    K[41] = 32'ha81a664b;
    K[42] = 32'hc24b8b70;
    K[43] = 32'hc76c51a3;
    K[44] = 32'hd192e819;
    K[45] = 32'hd6990624;
    K[46] = 32'hf40e3585;
    K[47] = 32'h106aa070;
    K[48] = 32'h19a4c116;
    K[49] = 32'h1e376c08;
    K[50] = 32'h2748774c;
    K[51] = 32'h34b0bcb5;
    K[52] = 32'h391c0cb3;
    K[53] = 32'h4ed8aa4a;
    K[54] = 32'h5b9cca4f;
    K[55] = 32'h682e6ff3;
    K[56] = 32'h748f82ee;
    K[57] = 32'h78a5636f;
    K[58] = 32'h84c87814;
    K[59] = 32'h8cc70208;
    K[60] = 32'h90befffa;
    K[61] = 32'ha4506ceb;
    K[62] = 32'hbef9a3f7;
    K[63] = 32'hc67178f2;
  end

  // =============================================
  // 中间计算信号
  // =============================================
  wire [31:0] T1 = h[0] + SIGMA1(e[0]) + Ch(e[0], f[0], g[0]) + K[wt_counter] + Wt_in;
  wire [31:0] T2 = SIGMA0(a[0]) + Maj(a[0], b[0], c[0]);
  wire [31:0] new_a = T1 + T2;
  wire [31:0] new_e = d[0] + T1;

  // =============================================
  // 主压缩逻辑
  // =============================================
  always @(posedge clk or negedge rst_n) begin
    if (!rst_n) begin
      // 复位所有寄存器
      for (integer i = 0; i < 32; i++) begin
        a[i] <= 0;
        b[i] <= 0;
        c[i] <= 0;
        d[i] <= 0;
        e[i] <= 0;
        f[i] <= 0;
        g[i] <= 0;
        h[i] <= 0;
      end
      hash_reg       <= 0;
      wt_counter     <= 0;
      zip_active     <= 0;
      output_stage   <= 0;
      hash_out       <= 0;
      hash_out_valid <= 0;
    end else begin

      // $display(
      //     "Wt_valid: %b, zip_active: %b, wt_counter: %d, output_stage: %b, hash_out_valid: %b, a[0]: %h, b[0]: %h, c[0]: %h, d[0]: %h, e[0]: %h, f[0]: %h, g[0]: %h, h[0]: %h",
      //     Wt_valid, zip_active, wt_counter, output_stage, hash_out_valid, a[0], b[0], c[0], d[0],
      //     e[0], f[0], g[0], h[0]);

      // 默认输出无效
      hash_out_valid <= 0;

      // ------------------------------
      // 压缩过程初始化
      // ------------------------------
      if (Wt_valid && !zip_active) begin
        // 初始化工作变量
        a[0] <= hash_in[255:224];
        b[0] <= hash_in[223:192];
        c[0] <= hash_in[191:160];
        d[0] <= hash_in[159:128];
        e[0] <= hash_in[127:96];
        f[0] <= hash_in[95:64];
        g[0] <= hash_in[63:32];
        h[0] <= hash_in[31:0];

        // 初始化其他寄存器
        for (integer i = 1; i < 32; i++) begin
          a[i] <= 0;
          b[i] <= 0;
          c[i] <= 0;
          d[i] <= 0;
          e[i] <= 0;
          f[i] <= 0;
          g[i] <= 0;
          h[i] <= 0;
        end

        // 立即用当前Wt值进行第一轮压缩
        a[0]       <= new_a;
        b[0]       <= hash_in[255:224];
        c[0]       <= hash_in[223:192];
        d[0]       <= hash_in[191:160];
        e[0]       <= new_e;
        f[0]       <= hash_in[127:96];
        g[0]       <= hash_in[95:64];
        h[0]       <= hash_in[63:32];

        hash_reg   <= hash_in;
        zip_active <= 1;
        wt_counter <= 0;
      end

      // ------------------------------
      // 压缩处理阶段
      // ------------------------------
      if (Wt_valid && zip_active) begin
        // 更新流水线寄存器 - 右移
        for (integer i = 31; i > 0; i--) begin
          a[i] <= a[i-1];
          b[i] <= b[i-1];
          c[i] <= c[i-1];
          d[i] <= d[i-1];
          e[i] <= e[i-1];
          f[i] <= f[i-1];
          g[i] <= g[i-1];
          h[i] <= h[i-1];
        end

        // 计算新的工作变量并存入第0级
        a[0] <= new_a;
        b[0] <= a[0];
        c[0] <= b[0];
        d[0] <= c[0];
        e[0] <= new_e;
        f[0] <= e[0];
        g[0] <= f[0];
        h[0] <= g[0];

        // 更新计数器
        wt_counter <= wt_counter + 1;
      end

      if (zip_active && wt_counter == 63) begin
        zip_active   <= 0;
        wt_counter   <= 0;
        output_stage <= 1;
      end

      // ------------------------------
      // 输出阶段
      // ------------------------------
      if (output_stage) begin
        // 计算最终哈希值
        hash_out <= {
          hash_reg[255:224] + a[0],
          hash_reg[223:192] + b[0],
          hash_reg[191:160] + c[0],
          hash_reg[159:128] + d[0],
          hash_reg[127:96] + e[0],
          hash_reg[95:64] + f[0],
          hash_reg[63:32] + g[0],
          hash_reg[31:0] + h[0]
        };

        hash_out_valid <= 1;
        output_stage <= 0;
      end
    end
  end

endmodule

compress_tb.v
`timescale 1ns / 1ps

module compress_tb ();

  // 时钟和复位信号
  reg clk;
  reg rst_n;

  // 压缩模块输入
  reg [31:0] Wt_in;
  reg Wt_valid;
  reg [255:0] hash_in;

  // 压缩模块输出
  wire [255:0] hash_out;
  wire hash_out_valid;

  // 测试向量
  reg [31:0] test_W[0:63];  // 测试用的Wt值
  reg [255:0] initial_hash;  // 初始哈希值

  // 实例化被测模块
  compress uut (
      .clk(clk),
      .rst_n(rst_n),
      .Wt_in(Wt_in),
      .Wt_valid(Wt_valid),
      .hash_in(hash_in),
      .hash_out(hash_out),
      .hash_out_valid(hash_out_valid)
  );

  // 时钟生成（周期10ns）
  initial begin
    clk = 0;
    forever #5 clk = ~clk;
  end

  // 测试过程
  initial begin
    // =============================================
    // 初始化测试向量
    // =============================================
    // 使用标准SHA-256测试向量
    initial_hash = 256'h6a09e667_bb67ae85_3c6ef372_a54ff53a_510e527f_9b05688c_1f83d9ab_5be0cd19;

    // 填充测试Wt值（来自"abc"消息的扩展结果）
    test_W[0] = 32'h61626380;
    test_W[1] = 32'h00000000;
    test_W[2] = 32'h00000000;
    test_W[3] = 32'h00000000;
    test_W[4] = 32'h00000000;
    test_W[5] = 32'h00000000;
    test_W[6] = 32'h00000000;
    test_W[7] = 32'h00000000;
    test_W[8] = 32'h00000000;
    test_W[9] = 32'h00000000;
    test_W[10] = 32'h00000000;
    test_W[11] = 32'h00000000;
    test_W[12] = 32'h00000000;
    test_W[13] = 32'h00000000;
    test_W[14] = 32'h00000000;
    test_W[15] = 32'h00000018;
    // 扩展部分
    test_W[16] = 32'h61626380;
    test_W[17] = 32'h000f0000;
    test_W[18] = 32'h7da86405;
    test_W[19] = 32'h00000000;
    test_W[20] = 32'h00000000;
    test_W[21] = 32'h00000000;
    test_W[22] = 32'h00000000;
    test_W[23] = 32'h00000000;
    test_W[24] = 32'h00000000;
    test_W[25] = 32'h00000000;
    test_W[26] = 32'h00000000;
    test_W[27] = 32'h00000000;
    test_W[28] = 32'h00000000;
    test_W[29] = 32'h00000000;
    test_W[30] = 32'h00000000;
    test_W[31] = 32'h00000000;
    test_W[32] = 32'h00000000;
    test_W[33] = 32'h00000000;
    test_W[34] = 32'h00000000;
    test_W[35] = 32'h00000000;
    test_W[36] = 32'h00000000;
    test_W[37] = 32'h00000000;
    test_W[38] = 32'h00000000;
    test_W[39] = 32'h00000000;
    test_W[40] = 32'h00000000;
    test_W[41] = 32'h00000000;
    test_W[42] = 32'h00000000;
    test_W[43] = 32'h00000000;
    test_W[44] = 32'h00000000;
    test_W[45] = 32'h00000000;
    test_W[46] = 32'h00000000;
    test_W[47] = 32'h00000000;
    test_W[48] = 32'h00000000;
    test_W[49] = 32'h00000000;
    test_W[50] = 32'h00000000;
    test_W[51] = 32'h00000000;
    test_W[52] = 32'h00000000;
    test_W[53] = 32'h00000000;
    test_W[54] = 32'h00000000;
    test_W[55] = 32'h00000000;
    test_W[56] = 32'h00000000;
    test_W[57] = 32'h00000000;
    test_W[58] = 32'h00000000;
    test_W[59] = 32'h00000000;
    test_W[60] = 32'h00000000;
    test_W[61] = 32'h00000000;
    test_W[62] = 32'h00000000;
    test_W[63] = 32'h12b1edeb;

    // =============================================
    // 测试用例1：基本功能测试
    // =============================================
    $display("\n[TEST CASE 1] Basic functionality test");

    // 初始化
    #20;
    rst_n = 0;
    Wt_in = 0;
    Wt_valid = 0;
    hash_in = 0;
    #10;

    // 释放复位
    rst_n = 1;
    #10;

    // 设置初始哈希值
    hash_in = initial_hash;

    // 开始发送Wt值
    for (integer t = 0; t < 64; t = t + 1) begin
      @(posedge clk);
      Wt_in = test_W[t];
      Wt_valid = 1;
      @(posedge clk);
      Wt_valid = 0;
    end

    // 等待最终哈希输出
    wait (hash_out_valid);
    #0.1;
    $display("First block final hash: %h", hash_out);

    // =============================================
    // 测试用例2：连续块处理测试
    // =============================================
    $display("\n[TEST CASE 2] Continuous block processing test");

    // 使用第一个块的输出作为第二个块的输入
    #20;
    hash_in = hash_out;

    // 发送第二个块的Wt值（使用不同的测试向量）
    for (integer t = 0; t < 64; t = t + 1) begin
      @(posedge clk);
      Wt_in = test_W[t] + 32'h100;  // 修改Wt值以模拟不同的消息块
      Wt_valid = 1;
      @(posedge clk);
      Wt_valid = 0;
    end

    // 等待最终哈希输出
    wait (hash_out_valid);
    #0.1;
    $display("Second block final hash: %h", hash_out);

    // =============================================
    // 测试用例3：边界条件测试 - 复位测试
    // =============================================
    $display("\n[TEST CASE 3] Reset test");

    // 在压缩过程中复位
    hash_in = initial_hash;

    // 开始发送Wt值
    for (integer t = 0; t < 16; t = t + 1) begin
      @(posedge clk);
      Wt_in = test_W[t];
      Wt_valid = 1;
      @(posedge clk);
      Wt_valid = 0;
    end

    // 在压缩过程中触发复位
    #50;
    rst_n = 0;
    #20;
    rst_n = 1;

    // 验证输出是否被复位
    if (hash_out_valid === 0) begin
      $display("[RESULT] PASS: Reset correctly deasserted hash_out_valid");
    end else begin
      $display("[RESULT] FAIL: Reset did not deassert hash_out_valid");
    end

    // =============================================
    // 结束仿真
    // =============================================
    #100;
    $display("\n[SIMULATION FINISHED]");
    $finish;
  end

  // 波形转储
  initial begin
    $dumpfile("compress.vcd");
    $dumpvars(0, compress_tb);
  end

endmodule

compress.vcd
$date
	Wed Jul 30 09:38:29 2025
$end
$version
	Icarus Verilog
$end
$timescale
	1ps
$end
$scope module compress_tb $end
$var wire 1 ! hash_out_valid $end
$var wire 256 " hash_out [255:0] $end
$var reg 32 # Wt_in [31:0] $end
$var reg 1 $ Wt_valid $end
$var reg 1 % clk $end
$var reg 256 & hash_in [255:0] $end
$var reg 256 ' initial_hash [255:0] $end
$var reg 1 ( rst_n $end
$scope module uut $end
$var wire 32 ) Wt_in [31:0] $end
$var wire 1 $ Wt_valid $end
$var wire 1 % clk $end
$var wire 256 * hash_in [255:0] $end
$var wire 1 ( rst_n $end
$var wire 32 + new_e [31:0] $end
$var wire 32 , new_a [31:0] $end
$var wire 32 - T2 [31:0] $end
$var wire 32 . T1 [31:0] $end
$var reg 256 / hash_out [255:0] $end
$var reg 1 ! hash_out_valid $end
$var reg 256 0 hash_reg [255:0] $end
$var reg 1 1 output_stage $end
$var reg 6 2 wt_counter [5:0] $end
$var reg 1 3 zip_active $end
$scope function Ch $end
$var reg 32 4 x [31:0] $end
$var reg 32 5 y [31:0] $end
$var reg 32 6 z [31:0] $end
$upscope $end
$scope function Maj $end
$var reg 32 7 x [31:0] $end
$var reg 32 8 y [31:0] $end
$var reg 32 9 z [31:0] $end
$upscope $end
$scope function SIGMA0 $end
$var reg 32 : x [31:0] $end
$upscope $end
$scope function SIGMA1 $end
$var reg 32 ; x [31:0] $end
$upscope $end
$scope begin $ivl_for_loop0 $end
$var integer 32 < i [31:0] $end
$upscope $end
$scope begin $ivl_for_loop1 $end
$var integer 32 = i [31:0] $end
$upscope $end
$scope begin $ivl_for_loop2 $end
$var integer 32 > i [31:0] $end
$upscope $end
$upscope $end
$scope begin $ivl_for_loop3 $end
$var integer 32 ? t [31:0] $end
$upscope $end
$scope begin $ivl_for_loop4 $end
$var integer 32 @ t [31:0] $end
$upscope $end
$scope begin $ivl_for_loop5 $end
$var integer 32 A t [31:0] $end
$upscope $end
$upscope $end
$enddefinitions $end
$comment Show the parameter values. $end
$dumpall
$end
#0
$dumpvars
bx A
bx @
bx ?
bx >
bx =
bx <
bx ;
bx :
bx 9
bx 8
bx 7
bx 6
bx 5
bx 4
x3
bx 2
x1
bx 0
bx /
bx .
bx -
bx ,
bx +
bx *
bx )
x(
b110101000001001111001100110011110111011011001111010111010000101001111000110111011110011011100101010010101001111111101010011101001010001000011100101001001111111100110110000010101101000100011000001111110000011110110011010101101011011111000001100110100011001 '
bx &
0%
x$
bx #
bx "
x!
$end
#5000
0!
1%
#10000
0%
#15000
1%
#20000
b1000010100010100010111110011000 ,
b1000010100010100010111110011000 +
b1000010100010100010111110011000 .
b0 ;
b0 6
b0 5
b0 4
b0 -
b0 :
b0 9
b0 8
b0 7
b0 "
b0 /
01
03
b0 2
b0 0
b100000 <
0%
b0 &
b0 *
0$
b0 #
b0 )
0(
#25000
b100000 <
1%
#30000
0%
1(
#35000
1%
#40000
0%
b0 ?
b110101000001001111001100110011110111011011001111010111010000101001111000110111011110011011100101010010101001111111101010011101001010001000011100101001001111111100110110000010101101000100011000001111110000011110110011010101101011011111000001100110100011001 &
b110101000001001111001100110011110111011011001111010111010000101001111000110111011110011011100101010010101001111111101010011101001010001000011100101001001111111100110110000010101101000100011000001111110000011110110011010101101011011111000001100110100011001 *
#45000
b10100011111011001001001100011000 ;
b10011011000001010110100010001100 6
b1010001000011100101001001111111 5
b10100011111011001001001100011000 4
b10100011111011001001001100011000 :
b10101101110111111111111100110010 -
b10111011011001111010111010000101 9
b1101010000010011110011001100111 8
b10100011111011001001001100011000 7
13
b110101000001001111001100110011110111011011001111010111010000101001111000110111011110011011100101010010101001111111101010011101001010001000011100101001001111111100110110000010101101000100011000001111110000011110110011010101101011011111000001100110100011001 0
b100000 =
1$
b10000010001100000010101000100000 ,
b10000101111110001111001100000 +
b11010100010100000010101011101110 .
b1100001011000100110001110000000 #
b1100001011000100110001110000000 )
1%
#50000
0%
#55000
b1 ?
0$
1%
#60000
0%
#65000
b10101111010111001011101011100000 ;
b1010001000011100101001001111111 6
b10100011111011001001001100011000 5
b10101111010111001011101011100000 4
b100000110011011100011010100000 :
b101100111101101011110101100101 -
b1101010000010011110011001100111 9
b10100011111011001001001100011000 8
b100000110011011100011010100000 7
b1 2
b0 >
1$
b10011101011110000010010111001100 ,
b101011111010010001011011101100 +
b1110000100000010110100001100111 .
b0 #
b0 )
1%
#70000
0%
#75000
b10 ?
0$
1%
#80000
0%
#85000
b101011111010010001011011101100 ;
b10100011111011001001001100011000 6
b10101111010111001011101011100000 5
b101011111010010001011011101100 4
b10011101011110000010010111001100 :
b10001011100110100101100001001111 -
b10100011111011001001001100011000 9
b100000110011011100011010100000 8
b10011101011110000010010111001100 7
b10 2
b11010111010101111110100111111001 ,
b1001011101111011001000110101010 .
b10110101110001110111100000010001 +
b0 >
1$
1%
#90000
0%
#95000
b11 ?
0$
1%
#100000
0%
#105000
b10110101110001110111100000010001 ;
b10101111010111001011101011100000 6
b101011111010010001011011101100 5
b10110101110001110111100000010001 4
b11010111010101111110100111111001 :
b11111011000110101000110110000100 -
b100000110011011100011010100000 9
b10011101011110000010010111001100 8
b11010111010101111110100111111001 7
b11 2
b1011011111101000011110011110110 ,
b1100000110110011010111101110010 .
b100110001100100001010001010 +
b0 >
1$
1%
#110000
0%
#115000
b100 ?
0$
1%
#120000
0%
#125000
b100110001100100001010001010 ;
b101011111010010001011011101100 6
b10110101110001110111100000010001 5
b100110001100100001010001010 4
b1011011111101000011110011110110 :
b10000001001100000011011111101111 -
b10011101011110000010010111001100 9
b11010111010101111110100111111001 8
b1011011111101000011110011110110 7
b100 2
b10110100010001011100111001001110 ,
b110011000101011001011001011111 .
b1010011111000110101110011111111 +
b0 >
1$
1%
#130000
0%
#135000
b101 ?
0$
1%
#140000
0%
#145000
b1010011111000110101110011111111 ;
b10110101110001110111100000010001 6
b100110001100100001010001010 5
b1010011111000110101110011111111 4
b10110100010001011100111001001110 :
b10011111101100111101100001101010 -
b11010111010101111110100111111001 9
b1011011111101000011110011110110 8
b10110100010001011100111001001110 7
b101 2
b1011101010111111111000010000010 ,
b10111101101011000001100000011000 .
b1011011001001000011110111100100 +
b0 >
1$
1%
#150000
0%
#155000
b110 ?
0$
1%
#160000
0%
#165000
b1011011001001000011110111100100 ;
b100110001100100001010001010 6
b1010011111000110101110011111111 5
b1011011001001000011110111100100 4
b1011101010111111111000010000010 :
b11001001110111010001110001110000 -
b1011011111101000011110011110110 9
b10110100010001011100111001001110 8
b1011101010111111111000010000010 7
b110 2
b101001101111110111110001110000 ,
b1011111111000100110000000000000 .
b110111001110100100100111111001 +
b0 >
1$
1%
#170000
0%
#175000
b111 ?
0$
1%
#180000
0%
#185000
b110111001110100100100111111001 ;
b1010011111000110101110011111111 6
b1011011001001000011110111100100 5
b110111001110100100100111111001 4
b101001101111110111110001110000 :
b1010001011111110100111010000011 -
b10110100010001011100111001001110 9
b1011101010111111111000010000010 8
b101001101111110111110001110000 7
b111 2
b10011100001000100000000010111101 ,
b1001010101000101011001000111010 .
b10100110100101101110111100110000 +
b0 >
1$
1%
#190000
0%
#195000
b1000 ?
0$
1%
#200000
0%
#205000
b10100110100101101110111100110000 ;
b1011011001001000011110111100100 6
b110111001110100100100111111001 5
b10100110100101101110111100110000 4
b10011100001000100000000010111101 :
b1000001001100000011111111111 -
b1011101010111111111000010000010 9
b101001101111110111110001110000 8
b10011100001000100000000010111101 7
b1000 2
b100011001111000111101010111100 ,
b11011000101100111001010111101 .
b11001111010111000100000100001011 +
b0 >
1$
1%
#210000
0%
#215000
b1001 ?
0$
1%
#220000
0%
#225000
b11001111010111000100000100001011 ;
b110111001110100100100111111001 6
b10100110100101101110111100110000 5
b11001111010111000100000100001011 4
b100011001111000111101010111100 :
b1010110000000110111000001111100 -
b101001101111110111110001110000 9
b10011100001000100000000010111101 8
b100011001111000111101010111100 7
b1001 2
b11010010001010111001010111100 ,
b11000100010000100000001001000000 .
b100001101000011111001011000010 +
b0 >
1$
1%
#230000
0%
#235000
b1010 ?
0$
1%
#240000
0%
#245000
b100001101000011111001011000010 ;
b10100110100101101110111100110000 6
b11001111010111000100000100001011 5
b100001101000011111001011000010 4
b11010010001010111001010111100 :
b10100000110111111111000110101001 -
b10011100001000100000000010111101 9
b100011001111000111101010111100 8
b11010010001010111001010111100 7
b1010 2
b11100111011110000101110111 ,
b1100010101111011110111111001110 .
b10001100011111010110110000111110 +
b0 >
1$
1%
#250000
0%
#255000
b1011 ?
0$
1%
#260000
0%
#265000
b10001100011111010110110000111110 ;
b11001111010111000100000100001011 6
b100001101000011111001011000010 5
b10001100011111010110110000111110 4
b11100111011110000101110111 :
b10111111111110000010101101111000 -
b100011001111000111101010111100 9
b11010010001010111001010111100 8
b11100111011110000101110111 7
b1011 2
b1000010000100110101111011001001 ,
b10000010000110110011001101010001 .
b11110001111010011010000001110 +
b0 >
1$
1%
#270000
0%
#275000
b1100 ?
0$
1%
#280000
0%
#285000
b11110001111010011010000001110 ;
b100001101000011111001011000010 6
b10001100011111010110110000111110 5
b11110001111010011010000001110 4
b1000010000100110101111011001001 :
b11101101110010110101010100011101 -
b11010010001010111001010111100 9
b11100111011110000101110111 8
b1000010000100110101111011001001 7
b1100 2
b100110001010000111011100011 ,
b10110111110011011100111000110 .
b111010001101100011010010000010 +
b0 >
1$
1%
#290000
0%
#295000
b1101 ?
0$
1%
#300000
0%
#305000
b111010001101100011010010000010 ;
b10001100011111010110110000111110 6
b11110001111010011010000001110 5
b111010001101100011010010000010 4
b100110001010000111011100011 :
b10100100101010000011100001100110 -
b11100111011110000101110111 9
b1000010000100110101111011001001 8
b100110001010000111011100011 7
b1101 2
b1101001010111000011100001101101 ,
b11000100101101000000000000000111 .
b11011110111110010111001011000011 +
b0 >
1$
1%
#310000
0%
#315000
b1110 ?
0$
1%
#320000
0%
#325000
b11011110111110010111001011000011 ;
b11110001111010011010000001110 6
b111010001101100011010010000010 5
b11011110111110010111001011000011 4
b1101001010111000011100001101101 :
b101010001100110001000001001000 -
b1000010000100110101111011001001 9
b100110001010000111011100011 8
b1101001010111000011100001101101 7
b1110 2
b10011000011110100001001011000101 ,
b1101110010001110000001001111101 .
b1110001111001001110001111110100 +
b0 >
1$
1%
#330000
0%
#335000
b1111 ?
0$
1%
#340000
0%
#345000
b1110001111001001110010000001100 ;
b111010001101100011010010000010 6
b11011110111110010111001011000011 5
b1110001111001001110010000001100 4
b10011000011110100001001011011101 :
b100001000101010100101111110011 -
b100110001010000111011100011 9
b1101001010111000011100001101101 8
b10011000011110100001001011011101 7
b1111 2
b0 >
1$
b10011110000111001000101101000011 ,
b10111111000110101001111000011001 +
b1111101000001110011111101010000 .
b11000 #
b11000 )
1%
#350000
0%
#355000
b10000 ?
0$
1%
#360000
0%
#365000
b100000011111010000000110000001 ;
b11011110111110010111001011000011 6
b1110001111001001110010000001100 5
b100000011111010000000110000001 4
b11111111011111101110111010101011 :
b1101010101110010010101010001101 -
b1101001010111000011100001101101 9
b10011000011110100001001011011101 8
b11111111011111101110111010101011 7
b10000 2
b0 >
1$
b11110011111101101101100111001000 ,
b10001110000000101011111000011110 +
b10001001001111011010111100111011 .
b1100001011000100110001110000000 #
b1100001011000100110001110000000 )
1%
#370000
0%
#375000
b10001 ?
0$
1%
#380000
0%
#385000
b101100101011110101101010011110 ;
b1110001111001001110010000001100 6
b100000011111010000000110000001 5
b101100101011110101101010011110 4
b10010010101000110111011001001000 :
b10110101101011111110000110001100 -
b10011000011110100001001011011101 9
b11111111011111101110111010101011 8
b10010010101000110111011001001000 7
b10001 2
b0 >
1$
b1110010101111101010011111101100 ,
b100110011010101111111011001101 +
b10111101000011101100011001100000 .
b11110000000000000000 #
b11110000000000000000 )
1%
#390000
0%
#395000
b10010 ?
0$
1%
#400000
0%
#405000
b10100100000001000110001011010010 ;
b100000011111010000000110000001 6
b101100101011110101101010011110 5
b10100100000001000110001011010010 4
b11110000010110000000101111110001 :
b110110001100001011011011100110 -
b11111111011111101110111010101011 9
b10010010101000110111011001001000 8
b11110000010110000000101111110001 7
b10010 2
b0 >
1$
b1101100111100101101100010100101 ,
b11001111001111000011010010011100 +
b110110110000100010000110111111 .
b1111101101010000110010000000101 #
b1111101101010000110010000000101 )
1%
#410000
0%
#415000
b10011 ?
0$
1%
#420000
0%
#425000
b1010001100100111101000010010111 ;
b101100101011110101101010011110 6
b10100100000001000110001011010010 5
b1010001100100111101000010010111 4
b11101111010010100111010010100000 :
b10101001010100011101101110100110 -
b10010010101000110111011001001000 9
b11110000010110000000101111110001 8
b11101111010010100111010010100000 7
b10011 2
b0 >
1$
b10100000010011000000000000011101 ,
b11110110011110010001001100100010 +
b11110110111110100010010001110111 .
b0 #
b0 )
1%
#430000
0%
#435000
b10100 ?
0$
1%
#440000
0%
#445000
b11110110011110010001001100100010 ;
b10100100000001000110001011010010 6
b1010001100100111101000010010111 5
b11110110011110010001001100100010 4
b10100000010011000000000000011101 :
b111001010001100111010110010111 -
b11110000010110000000101111110001 9
b11101111010010100111010010100000 8
b10100000010011000000000000011101 7
b10100 2
b10110111000000110010011110001011 ,
b1111101101111001011000111110100 .
b10000011000000010100000111100 +
b0 >
1$
1%
#450000
0%
#455000
b10101 ?
0$
1%
#460000
0%
#465000
b10000011000000010100000111100 ;
b1010001100100111101000010010111 6
b11110110011110010001001100100010 5
b10000011000000010100000111100 4
b10110111000000110010011110001011 :
b10000100010011011000001110110000 -
b11101111010010100111010010100000 9
b10100000010011000000000000011101 8
b10110111000000110010011110001011 7
b10101 2
b10001100100100011100111001111100 ,
b1000010001000100101011001100 .
b11111000100111000101011010111101 +
b0 >
1$
1%
#470000
0%
#475000
b10110 ?
0$
1%
#480000
0%
#485000
b11111000100111000101011010111101 ;
b11110110011110010001001100100010 6
b10000011000000010100000111100 5
b11111000100111000101011010111101 4
b10001100100100011100111001111100 :
b10111011111110101110101101000000 -
b10100000010011000000000000011101 9
b10110111000000110010011110001011 8
b10001100100100011100111001111100 7
b10110 2
b11101111000101101010001100011101 ,
b110011000110111011011111011101 .
b100010011001100010110001111101 +
b0 >
1$
1%
#490000
0%
#495000
b10111 ?
0$
1%
#500000
0%
#505000
b100010011001100010110001111101 ;
b10000011000000010100000111100 6
b11111000100111000101011010111101 5
b100010011001100010110001111101 4
b11101111000101101010001100011101 :
b11101000101110100100111011101011 -
b10110111000000110010011110001011 9
b10001100100100011100111001111100 8
b11101111000101101010001100011101 7
b10111 2
b11001110011011001101101000001001 ,
b11100101101100101000101100011110 .
b10000101111111101000101100111011 +
b0 >
1$
1%
#510000
0%
#515000
b11000 ?
0$
1%
#520000
0%
#525000
b10000101111111101000101100111011 ;
b11111000100111000101011010111101 6
b100010011001100010110001111101 5
b10000101111111101000101100111011 4
b11001110011011001101101000001001 :
b11011110110100100010110011111010 -
b10001100100100011100111001111100 9
b11101111000101101010001100011101 8
b11001110011011001101101000001001 7
b11000 2
b1110101111110011101101110000100 ,
b10010111001001111010111010001010 .
b1001110001010101101011000010101 +
b0 >
1$
1%
#530000
0%
#535000
b11001 ?
0$
1%
#540000
0%
#545000
b1001110001010101101011000010101 ;
b100010011001100010110001111101 6
b10000101111111101000101100111011 5
b1001110001010101101011000010101 4
b1110101111110011101101110000100 :
b10101101100001010010000000101 -
b11101111000101101010001100011101 9
b11001110011011001101101000001001 8
b1110101111110011101101110000100 7
b11001 2
b1011101111001111101000001001101 ,
b1001000001101110010110001001000 .
b11010100110010001111101011000100 +
b0 >
1$
1%
#550000
0%
#555000
b11010 ?
0$
1%
#560000
0%
#565000
b11010100110010001111101011000100 ;
b10000101111111101000101100111011 6
b1001110001010101101011000010101 5
b11010100110010001111101011000100 4
b1011101111001111101000001001101 :
b10101000010000000000100001100111 -
b11001110011011001101101000001001 9
b1110101111110011101101110000100 8
b1011101111001111101000001001101 7
b11010 2
b11101111100111010000100010001001 ,
b1000111010111010000000000100010 .
b110110011100111010001100111111 +
b0 >
1$
1%
#570000
0%
#575000
b11011 ?
0$
1%
#580000
0%
