compress.v
/*
 * 模块名称：compress
 *
 * 功能描述：
 *   本模块实现SHA-256算法的压缩函数部分，采用32级流水线结构。
 *   输出最终的哈希值。
 *
 * 主要特点：
 *   1. 32级流水线处理64个Wt
 *   2. 完全同步设计，与扩展模块时钟对齐
 *   3. 支持连续块处理，保持高吞吐量
 */

module compress (
    input              clk,
    input              rst_n,
    input      [ 31:0] Wt_in,          // 来自消息扩展的Wt (Wt0-Wt63)
    input              Wt_valid,       // Wt输入有效信号
    input      [255:0] hash_in,        // 初始哈希值或前一块的哈希
    output reg [255:0] hash_out,       // 压缩后的哈希值
    output reg         hash_out_valid  // 哈希输出有效信号
);

  // =============================================
  // 内部寄存器定义
  // =============================================
  reg [ 31:0] K                                        [0:63];  // SHA-256常量

  // 32级流水线寄存器
  reg [ 31:0] a                                        [0:31];  // a工作变量流水线
  reg [ 31:0] b                                        [0:31];  // b工作变量流水线
  reg [ 31:0] c                                        [0:31];  // c工作变量流水线
  reg [ 31:0] d                                        [0:31];  // d工作变量流水线
  reg [ 31:0] e                                        [0:31];  // e工作变量流水线
  reg [ 31:0] f                                        [0:31];  // f工作变量流水线
  reg [ 31:0] g                                        [0:31];  // g工作变量流水线
  reg [ 31:0] h                                        [0:31];  // h工作变量流水线

  reg [255:0] hash_reg;  // 输入哈希值寄存器
  reg [  5:0] wt_counter;  // Wt计数器 (0-63)
  reg         zip_active;  // 压缩过程激活标志
  reg         output_stage;  // 输出阶段标志

  // =============================================
  // Σ函数定义
  // =============================================
  function [31:0] SIGMA0;
    input [31:0] x;
    SIGMA0 = {x[1:0], x[31:2]} ^ {x[12:0], x[31:13]} ^ {x[21:0], x[31:22]};
  endfunction

  function [31:0] SIGMA1;
    input [31:0] x;
    SIGMA1 = {x[5:0], x[31:6]} ^ {x[10:0], x[31:11]} ^ {x[24:0], x[31:25]};
  endfunction

  // =============================================
  // 选择函数和多数函数
  // =============================================
  function [31:0] Ch;
    input [31:0] x, y, z;
    Ch = (x & y) ^ (~x & z);
  endfunction

  function [31:0] Maj;
    input [31:0] x, y, z;
    Maj = (x & y) ^ (x & z) ^ (y & z);
  endfunction

  // =============================================
  // 常量初始化
  // =============================================
  initial begin
    K[0]  = 32'h428a2f98;
    K[1]  = 32'h71374491;
    K[2]  = 32'hb5c0fbcf;
    K[3]  = 32'he9b5dba5;
    K[4]  = 32'h3956c25b;
    K[5]  = 32'h59f111f1;
    K[6]  = 32'h923f82a4;
    K[7]  = 32'hab1c5ed5;
    K[8]  = 32'hd807aa98;
    K[9]  = 32'h12835b01;
    K[10] = 32'h243185be;
    K[11] = 32'h550c7dc3;
    K[12] = 32'h72be5d74;
    K[13] = 32'h80deb1fe;
    K[14] = 32'h9bdc06a7;
    K[15] = 32'hc19bf174;
    K[16] = 32'he49b69c1;
    K[17] = 32'hefbe4786;
    K[18] = 32'h0fc19dc6;
    K[19] = 32'h240ca1cc;
    K[20] = 32'h2de92c6f;
    K[21] = 32'h4a7484aa;
    K[22] = 32'h5cb0a9dc;
    K[23] = 32'h76f988da;
    K[24] = 32'h983e5152;
    K[25] = 32'ha831c66d;
    K[26] = 32'hb00327c8;
    K[27] = 32'hbf597fc7;
    K[28] = 32'hc6e00bf3;
    K[29] = 32'hd5a79147;
    K[30] = 32'h06ca6351;
    K[31] = 32'h14292967;
    K[32] = 32'h27b70a85;
    K[33] = 32'h2e1b2138;
    K[34] = 32'h4d2c6dfc;
    K[35] = 32'h53380d13;
    K[36] = 32'h650a7354;
    K[37] = 32'h766a0abb;
    K[38] = 32'h81c2c92e;
    K[39] = 32'h92722c85;
    K[40] = 32'ha2bfe8a1;
    K[41] = 32'ha81a664b;
    K[42] = 32'hc24b8b70;
    K[43] = 32'hc76c51a3;
    K[44] = 32'hd192e819;
    K[45] = 32'hd6990624;
    K[46] = 32'hf40e3585;
    K[47] = 32'h106aa070;
    K[48] = 32'h19a4c116;
    K[49] = 32'h1e376c08;
    K[50] = 32'h2748774c;
    K[51] = 32'h34b0bcb5;
    K[52] = 32'h391c0cb3;
    K[53] = 32'h4ed8aa4a;
    K[54] = 32'h5b9cca4f;
    K[55] = 32'h682e6ff3;
    K[56] = 32'h748f82ee;
    K[57] = 32'h78a5636f;
    K[58] = 32'h84c87814;
    K[59] = 32'h8cc70208;
    K[60] = 32'h90befffa;
    K[61] = 32'ha4506ceb;
    K[62] = 32'hbef9a3f7;
    K[63] = 32'hc67178f2;
  end

  // =============================================
  // 中间计算信号
  // =============================================
  reg [31:0] a0, b0, c0, d0, e0, f0, g0, h0;
  reg [31:0] T1, T2;

  // =============================================
  // 主压缩逻辑
  // =============================================
  always @(posedge clk or negedge rst_n) begin
    if (!rst_n) begin
      // 复位所有寄存器
      for (integer i = 0; i < 32; i++) begin
        a[i] <= 0;
        b[i] <= 0;
        c[i] <= 0;
        d[i] <= 0;
        e[i] <= 0;
        f[i] <= 0;
        g[i] <= 0;
        h[i] <= 0;
      end
      hash_reg       <= 0;
      wt_counter     <= 0;
      zip_active     <= 0;
      output_stage   <= 0;
      hash_out       <= 0;
      hash_out_valid <= 0;
    end else begin
      // 默认输出无效
      hash_out_valid <= 0;

      // ------------------------------
      // 压缩过程初始化
      // ------------------------------
      if (Wt_valid && !zip_active) begin
        // 处理第一个Wt
        a0 = hash_in[255:224];
        b0 = hash_in[223:192];
        c0 = hash_in[191:160];
        d0 = hash_in[159:128];
        e0 = hash_in[127:96];
        f0 = hash_in[95:64];
        g0 = hash_in[63:32];
        h0 = hash_in[31:0];
        T1 = h0 + SIGMA1(e0) + Ch(e0, f0, g0) + K[0] + Wt_in;
        T2 = SIGMA0(a0) + Maj(a0, b0, c0);

        a[0] <= T1 + T2;
        b[0] <= a0;
        c[0] <= b0;
        d[0] <= c0;
        e[0] <= d0 + T1;
        f[0] <= e0;
        g[0] <= f0;
        h[0] <= g0;

        // 初始化其他寄存器
        for (integer i = 1; i < 32; i++) begin
          a[i] <= 0;
          b[i] <= 0;
          c[i] <= 0;
          d[i] <= 0;
          e[i] <= 0;
          f[i] <= 0;
          g[i] <= 0;
          h[i] <= 0;
        end

        hash_reg   <= hash_in;
        zip_active <= 1;
        wt_counter <= 0;
      end

      // ------------------------------
      // 压缩处理阶段
      // ------------------------------
      if (Wt_valid && zip_active) begin
        a0 = a[0];
        b0 = b[0];
        c0 = c[0];
        d0 = d[0];
        e0 = e[0];
        f0 = f[0];
        g0 = g[0];
        h0 = h[0];

        // 更新流水线寄存器 - 右移
        for (integer i = 31; i > 0; i--) begin
          a[i] <= a[i-1];
          b[i] <= b[i-1];
          c[i] <= c[i-1];
          d[i] <= d[i-1];
          e[i] <= e[i-1];
          f[i] <= f[i-1];
          g[i] <= g[i-1];
          h[i] <= h[i-1];
        end

        // 计算新的工作变量并存入第0级
        T1 = h0 + SIGMA1(e0) + Ch(e0, f0, g0) + K[wt_counter+1] + Wt_in;
        T2 = SIGMA0(a0) + Maj(a0, b0, c0);
        a[0] <= T1 + T2;
        b[0] <= a0;
        c[0] <= b0;
        d[0] <= c0;
        e[0] <= d0 + T1;
        f[0] <= e0;
        g[0] <= f0;
        h[0] <= g0;

        // 更新计数器
        wt_counter <= wt_counter + 1;
      end

      // ------------------------------
      // 64个Wt处理完毕后，结束压缩过程
      // ------------------------------
      if (zip_active && wt_counter == 63) begin
        zip_active   <= 0;
        wt_counter   <= 0;
        output_stage <= 1;
      end

      // ------------------------------
      // 输出阶段
      // ------------------------------
      if (output_stage) begin
        // 计算最终哈希值
        hash_out <= {
          hash_reg[255:224] + a[0],
          hash_reg[223:192] + b[0],
          hash_reg[191:160] + c[0],
          hash_reg[159:128] + d[0],
          hash_reg[127:96] + e[0],
          hash_reg[95:64] + f[0],
          hash_reg[63:32] + g[0],
          hash_reg[31:0] + h[0]
        };

        hash_out_valid <= 1;
        output_stage <= 0;
      end
    end
  end

endmodule

compress_tb.v
`timescale 1ns / 1ps

module compress_tb ();

  // 时钟和复位信号
  reg clk;
  reg rst_n;

  // 压缩模块输入
  reg [31:0] Wt_in;
  reg Wt_valid;
  reg [255:0] hash_in;

  // 压缩模块输出
  wire [255:0] hash_out;
  wire hash_out_valid;

  // 测试向量
  reg [31:0] test_W[0:63];  // 测试用的Wt值
  reg [255:0] initial_hash;  // 初始哈希值

  // 实例化被测模块
  compress uut (
      .clk(clk),
      .rst_n(rst_n),
      .Wt_in(Wt_in),
      .Wt_valid(Wt_valid),
      .hash_in(hash_in),
      .hash_out(hash_out),
      .hash_out_valid(hash_out_valid)
  );

  // 时钟生成（周期10ns）
  initial begin
    clk = 0;
    forever #5 clk = ~clk;
  end

  // 测试过程
  initial begin
    // =============================================
    // 初始化测试向量
    // =============================================
    // 使用标准SHA-256测试向量
    initial_hash = 256'h6a09e667_bb67ae85_3c6ef372_a54ff53a_510e527f_9b05688c_1f83d9ab_5be0cd19;

    // 填充测试Wt值（来自"abc"消息的扩展结果）
    test_W[0] = 32'h61626380;
    test_W[1] = 32'h00000000;
    test_W[2] = 32'h00000000;
    test_W[3] = 32'h00000000;
    test_W[4] = 32'h00000000;
    test_W[5] = 32'h00000000;
    test_W[6] = 32'h00000000;
    test_W[7] = 32'h00000000;
    test_W[8] = 32'h00000000;
    test_W[9] = 32'h00000000;
    test_W[10] = 32'h00000000;
    test_W[11] = 32'h00000000;
    test_W[12] = 32'h00000000;
    test_W[13] = 32'h00000000;
    test_W[14] = 32'h00000000;
    test_W[15] = 32'h00000018;
    // 扩展部分
    test_W[16] = 32'h61626380;
    test_W[17] = 32'h000f0000;
    test_W[18] = 32'h7da86405;
    test_W[19] = 32'h600003c6;
    test_W[20] = 32'h3e9d7b78;
    test_W[21] = 32'h0183fc00;
    test_W[22] = 32'h12dcbfdb;
    test_W[23] = 32'he2e2c38e;
    test_W[24] = 32'hc8215c1a;
    test_W[25] = 32'hb73679a2;
    test_W[26] = 32'he5bc3909;
    test_W[27] = 32'h32663c5b;
    test_W[28] = 32'h9d209d67;
    test_W[29] = 32'hec8726cb;
    test_W[30] = 32'h702138a4;
    test_W[31] = 32'hd3b7973b;
    test_W[32] = 32'h93f5997f;
    test_W[33] = 32'h3b68ba73;
    test_W[34] = 32'haff4ffc1;
    test_W[35] = 32'hf10a5c62;
    test_W[36] = 32'h0a8b3996;
    test_W[37] = 32'h72af830a;
    test_W[38] = 32'h9409e33e;
    test_W[39] = 32'h24641522;
    test_W[40] = 32'h9f47bf94;
    test_W[41] = 32'hf0a64f5a;
    test_W[42] = 32'h3e246a79;
    test_W[43] = 32'h27333ba3;
    test_W[44] = 32'h0c4763f2;
    test_W[45] = 32'h840abf27;
    test_W[46] = 32'h7a290d5d;
    test_W[47] = 32'h065c43da;
    test_W[48] = 32'hfb3e89cb;
    test_W[49] = 32'hcc7617db;
    test_W[50] = 32'hb9e66c34;
    test_W[51] = 32'ha9993667;
    test_W[52] = 32'h84badedd;
    test_W[53] = 32'hc21462bc;
    test_W[54] = 32'h1487472c;
    test_W[55] = 32'hb20f7a99;
    test_W[56] = 32'hef57b9cd;
    test_W[57] = 32'hebe6b238;
    test_W[58] = 32'h9fe3095e;
    test_W[59] = 32'h78bc8d4b;
    test_W[60] = 32'ha43fcf15;
    test_W[61] = 32'h668b2ff8;
    test_W[62] = 32'heeaba2cc;
    test_W[63] = 32'h12b1edeb;

    // =============================================
    // 测试用例1：基本功能测试
    // =============================================
    $display("\n[TEST CASE 1] Basic functionality test");

    // 初始化
    #20;
    rst_n = 0;
    Wt_in = 0;
    Wt_valid = 0;
    hash_in = 0;
    #10;

    // 释放复位
    rst_n = 1;
    #10;

    // 设置初始哈希值
    hash_in = initial_hash;

    // 开始发送Wt值
    for (integer t = 0; t < 64; t = t + 1) begin
      @(posedge clk);
      Wt_in = test_W[t];
      Wt_valid = 1;
      @(posedge clk);
      Wt_valid = 0;
    end

    // 等待最终哈希输出
    wait (hash_out_valid);
    #0.1;
    $display("First block final hash: %h", hash_out);

    // =============================================
    // 测试用例2：连续块处理测试
    // =============================================
    $display("\n[TEST CASE 2] Continuous block processing test");

    // 使用第一个块的输出作为第二个块的输入
    #20;
    hash_in = hash_out;

    // 发送第二个块的Wt值（使用不同的测试向量）
    for (integer t = 0; t < 64; t = t + 1) begin
      @(posedge clk);
      Wt_in = test_W[t];  // 修改Wt值以模拟不同的消息块
      Wt_valid = 1;
      @(posedge clk);
      Wt_valid = 0;
    end

    // 等待最终哈希输出
    wait (hash_out_valid);
    #0.1;
    $display("Second block final hash: %h", hash_out);

    // =============================================
    // 测试用例3：边界条件测试 - 复位测试
    // =============================================
    $display("\n[TEST CASE 3] Reset test");

    // 在压缩过程中复位
    hash_in = initial_hash;

    // 开始发送Wt值
    for (integer t = 0; t < 16; t = t + 1) begin
      @(posedge clk);
      Wt_in = test_W[t];
      Wt_valid = 1;
      @(posedge clk);
      Wt_valid = 0;
    end

    // 在压缩过程中触发复位
    #50;
    rst_n = 0;
    #20;
    rst_n = 1;

    // 验证输出是否被复位
    if (hash_out_valid === 0) begin
      $display("[RESULT] PASS: Reset correctly deasserted hash_out_valid");
    end else begin
      $display("[RESULT] FAIL: Reset did not deassert hash_out_valid");
    end

    // =============================================
    // 结束仿真
    // =============================================
    #100;
    $display("\n[SIMULATION FINISHED]");
    $finish;
  end

  // 波形转储
  initial begin
    $dumpfile("compress.vcd");
    $dumpvars(0, compress_tb);
  end

endmodule

compress.vcd
$date
	Thu Jul 31 09:15:48 2025
$end
$version
	Icarus Verilog
$end
$timescale
	1ps
$end
$scope module compress_tb $end
$var wire 1 ! hash_out_valid $end
$var wire 256 " hash_out [255:0] $end
$var reg 32 # Wt_in [31:0] $end
$var reg 1 $ Wt_valid $end
$var reg 1 % clk $end
$var reg 256 & hash_in [255:0] $end
$var reg 256 ' initial_hash [255:0] $end
$var reg 1 ( rst_n $end
$scope module uut $end
$var wire 32 ) Wt_in [31:0] $end
$var wire 1 $ Wt_valid $end
$var wire 1 % clk $end
$var wire 256 * hash_in [255:0] $end
$var wire 1 ( rst_n $end
$var reg 32 + T1 [31:0] $end
$var reg 32 , T2 [31:0] $end
$var reg 32 - a0 [31:0] $end
$var reg 32 . b0 [31:0] $end
$var reg 32 / c0 [31:0] $end
$var reg 32 0 d0 [31:0] $end
$var reg 32 1 e0 [31:0] $end
$var reg 32 2 f0 [31:0] $end
$var reg 32 3 g0 [31:0] $end
$var reg 32 4 h0 [31:0] $end
$var reg 256 5 hash_out [255:0] $end
$var reg 1 ! hash_out_valid $end
$var reg 256 6 hash_reg [255:0] $end
$var reg 1 7 output_stage $end
$var reg 6 8 wt_counter [5:0] $end
$var reg 1 9 zip_active $end
$scope function Ch $end
$var reg 32 : x [31:0] $end
$var reg 32 ; y [31:0] $end
$var reg 32 < z [31:0] $end
$upscope $end
$scope function Maj $end
$var reg 32 = x [31:0] $end
$var reg 32 > y [31:0] $end
$var reg 32 ? z [31:0] $end
$upscope $end
$scope function SIGMA0 $end
$var reg 32 @ x [31:0] $end
$upscope $end
$scope function SIGMA1 $end
$var reg 32 A x [31:0] $end
$upscope $end
$scope begin $ivl_for_loop0 $end
$var integer 32 B i [31:0] $end
$upscope $end
$scope begin $ivl_for_loop1 $end
$var integer 32 C i [31:0] $end
$upscope $end
$scope begin $ivl_for_loop2 $end
$var integer 32 D i [31:0] $end
$upscope $end
$upscope $end
$scope begin $ivl_for_loop3 $end
$var integer 32 E t [31:0] $end
$upscope $end
$scope begin $ivl_for_loop4 $end
$var integer 32 F t [31:0] $end
$upscope $end
$scope begin $ivl_for_loop5 $end
$var integer 32 G t [31:0] $end
$upscope $end
$upscope $end
$enddefinitions $end
$comment Show the parameter values. $end
$dumpall
$end
#0
$dumpvars
bx G
bx F
bx E
bx D
bx C
bx B
bx A
bx @
bx ?
bx >
bx =
bx <
bx ;
bx :
x9
bx 8
x7
bx 6
bx 5
bx 4
bx 3
bx 2
bx 1
bx 0
bx /
bx .
bx -
bx ,
bx +
bx *
bx )
x(
b110101000001001111001100110011110111011011001111010111010000101001111000110111011110011011100101010010101001111111101010011101001010001000011100101001001111111100110110000010101101000100011000001111110000011110110011010101101011011111000001100110100011001 '
bx &
0%
x$
bx #
bx "
x!
$end
#5000
0!
1%
#10000
0%
#15000
1%
#20000
b0 "
b0 5
07
09
b0 8
b0 6
b100000 B
0%
b0 &
b0 *
0$
b0 #
b0 )
0(
#25000
b100000 B
1%
#30000
0%
1(
#35000
1%
#40000
0%
b0 E
b110101000001001111001100110011110111011011001111010111010000101001111000110111011110011011100101010010101001111111101010011101001010001000011100101001001111111100110110000010101101000100011000001111110000011110110011010101101011011111000001100110100011001 &
b110101000001001111001100110011110111011011001111010111010000101001111000110111011110011011100101010010101001111111101010011101001010001000011100101001001111111100110110000010101101000100011000001111110000011110110011010101101011011111000001100110100011001 *
#45000
19
b110101000001001111001100110011110111011011001111010111010000101001111000110111011110011011100101010010101001111111101010011101001010001000011100101001001111111100110110000010101101000100011000001111110000011110110011010101101011011111000001100110100011001 6
b100000 C
b1000100100001001101011100101 ,
b1101010000010011110011001100111 =
b10111011011001111010111010000101 >
b111100011011101111001101110010 ?
b1101010000010011110011001100111 @
b1010100110110100101000011101000 +
b1010001000011100101001001111111 :
b10011011000001010110100010001100 ;
b11111100000111101100110101011 <
b1010001000011100101001001111111 A
b1011011111000001100110100011001 4
b11111100000111101100110101011 3
b10011011000001010110100010001100 2
b1010001000011100101001001111111 1
b10100101010011111111010100111010 0
b111100011011101111001101110010 /
b10111011011001111010111010000101 .
b1101010000010011110011001100111 -
1$
b1100001011000100110001110000000 #
b1100001011000100110001110000000 )
1%
#50000
0%
#55000
b1 E
0$
1%
#60000
0%
#65000
b1 8
b11110000010110101001110010110 ,
b1011101011010101110101111001101 =
b1101010000010011110011001100111 >
b10111011011001111010111010000101 ?
b1011101011010101110101111001101 @
b111100010111111000011000010111 +
b11111010001010100100011000100010 :
b1010001000011100101001001111111 ;
b10011011000001010110100010001100 <
b11111010001010100100011000100010 A
b0 D
b11111100000111101100110101011 4
b10011011000001010110100010001100 3
b1010001000011100101001001111111 2
b11111010001010100100011000100010 1
b111100011011101111001101110010 0
b10111011011001111010111010000101 /
b1101010000010011110011001100111 .
b1011101011010101110101111001101 -
1$
b0 #
b0 )
1%
#70000
0%
#75000
b10 E
0$
1%
#80000
0%
#85000
b10 8
b10001011000000011011110001000001 ,
b1011010011010101101100110101101 =
b1011101011010101110101111001101 >
b1101010000010011110011001100111 ?
b1011010011010101101100110101101 @
b111101110000011000101101100110 +
b1111000110011100111100110001001 :
b11111010001010100100011000100010 ;
b1010001000011100101001001111111 <
b1111000110011100111100110001001 A
b0 D
b10011011000001010110100010001100 4
b1010001000011100101001001111111 3
b11111010001010100100011000100010 2
b1111000110011100111100110001001 1
b10111011011001111010111010000101 0
b1101010000010011110011001100111 /
b1011101011010101110101111001101 .
b1011010011010101101100110101101 -
1$
1%
#90000
0%
#95000
b11 E
0$
1%
#100000
0%
#105000
b11 8
b11010011110101101010001111101 ,
b11001000110000110100011110100111 =
b1011010011010101101100110101101 >
b1011101011010101110101111001101 ?
b11001000110000110100011110100111 @
b10111010110101100010000111101001 +
b11111001001010010011100111101011 :
b1111000110011100111100110001001 ;
b11111010001010100100011000100010 <
b11111001001010010011100111101011 A
b0 D
b1010001000011100101001001111111 4
b11111010001010100100011000100010 3
b1111000110011100111100110001001 2
b11111001001010010011100111101011 1
b1101010000010011110011001100111 0
b1011101011010101110101111001101 /
b1011010011010101101100110101101 .
b11001000110000110100011110100111 -
1$
1%
#110000
0%
#115000
b100 E
0$
1%
#120000
0%
#125000
b100 8
b11101111111011110001111110010 ,
b11010101010100001111011001100110 =
b11001000110000110100011110100111 >
b1011010011010101101100110101101 ?
b11010101010100001111011001100110 @
b11100110010000101011011001111000 +
b100100111000000000100001010000 :
b11111001001010010011100111101011 ;
b1111000110011100111100110001001 <
b100100111000000000100001010000 A
b0 D
b11111010001010100100011000100010 4
b1111000110011100111100110001001 3
b11111001001010010011100111101011 2
b100100111000000000100001010000 1
b1011101011010101110101111001101 0
b1011010011010101101100110101101 /
b11001000110000110100011110100111 .
b11010101010100001111011001100110 -
1$
1%
#130000
0%
#135000
b101 E
0$
1%
#140000
0%
#145000
b101 8
b10100011010101000001011110101 ,
b100010000001001101001101010 =
b11010101010100001111011001100110 >
b11001000110000110100011110100111 ?
b100010000001001101001101010 @
b10110110101111000011100000000 +
b1000011101011011010001001000101 :
b100100111000000000100001010000 ;
b11111001001010010011100111101011 <
b1000011101011011010001001000101 A
b0 D
b1111000110011100111100110001001 4
b11111001001010010011100111101011 3
b100100111000000000100001010000 2
b1000011101011011010001001000101 1
b1011010011010101101100110101101 0
b11001000110000110100011110100111 /
b11010101010100001111011001100110 .
b100010000001001101001101010 -
1$
1%
#150000
0%
#155000
b110 E
0$
1%
#160000
0%
#165000
b110 8
b10010100111101010011100100110 ,
b101011010000100000100111110101 =
b100010000001001101001101010 >
b11010101010100001111011001100110 ?
b101011010000100000100111110101 @
b11010010011001000101110001011010 +
b1110001010000100110000010101101 :
b1000011101011011010001001000101 ;
b100100111000000000100001010000 <
b1110001010000100110000010101101 A
b0 D
b11111001001010010011100111101011 4
b100100111000000000100001010000 3
b1000011101011011010001001000101 2
b1110001010000100110000010101101 1
b11001000110000110100011110100111 0
b11010101010100001111011001100110 /
b100010000001001101001101010 .
b101011010000100000100111110101 -
1$
1%
#170000
0%
#175000
b111 E
0$
1%
#180000
0%
#185000
b111 8
b1001110100010111111011101001100 ,
b11100101000000110000001110000000 =
b101011010000100000100111110101 >
b100010000001001101001101010 ?
b11100101000000110000001110000000 @
b110111000101001000010000010011 +
b10011011001001111010010000000001 :
b1110001010000100110000010101101 ;
b1000011101011011010001001000101 <
b10011011001001111010010000000001 A
b0 D
b100100111000000000100001010000 4
b1000011101011011010001001000101 3
b1110001010000100110000010101101 2
b10011011001001111010010000000001 1
b11010101010100001111011001100110 0
b100010000001001101001101010 /
b101011010000100000100111110101 .
b11100101000000110000001110000000 -
1$
1%
#190000
0%
#195000
b1000 E
0$
1%
#200000
0%
#205000
b1000 8
b1011111011110110101100110010111 ,
b10000101101000000111101101011111 =
b11100101000000110000001110000000 >
b101011010000100000100111110101 ?
b10000101101000000111101101011111 @
b101110100010011001001100100010 +
b1100011001010111101001111001 :
b10011011001001111010010000000001 ;
b1110001010000100110000010101101 <
b1100011001010111101001111001 A
b0 D
b1000011101011011010001001000101 4
b1110001010000100110000010101101 3
b10011011001001111010010000000001 2
b1100011001010111101001111001 1
b100010000001001101001101010 0
b101011010000100000100111110101 /
b11100101000000110000001110000000 .
b10000101101000000111101101011111 -
1$
1%
#210000
0%
#215000
b1001 E
0$
1%
#220000
0%
#225000
b1001 8
b10011011000000000001100011001010 ,
b10001110000001001110110010111001 =
b10000101101000000111101101011111 >
b11100101000000110000001110000000 ?
b10001110000001001110110010111001 @
b11110001100001110001101110100001 +
b110010110010100010110110001100 :
b1100011001010111101001111001 ;
b10011011001001111010010000000001 <
b110010110010100010110110001100 A
b0 D
b1110001010000100110000010101101 4
b10011011001001111010010000000001 3
b1100011001010111101001111001 2
b110010110010100010110110001100 1
b101011010000100000100111110101 0
b11100101000000110000001110000000 /
b10000101101000000111101101011111 .
b10001110000001001110110010111001 -
1$
1%
#230000
0%
#235000
b1010 E
0$
1%
#240000
0%
#245000
b1010 8
b11101001001100001000001110001100 ,
b10001100100001110011010001101011 =
b10001110000001001110110010111001 >
b10000101101000000111101101011111 ?
b10001100100001110011010001101011 @
b1011110011010000010000001101000 +
b11100110010010010010110010110 :
b110010110010100010110110001100 ;
b1100011001010111101001111001 <
b11100110010010010010110010110 A
b0 D
b10011011001001111010010000000001 4
b1100011001010111101001111001 3
b110010110010100010110110001100 2
b11100110010010010010110010110 1
b11100101000000110000001110000000 0
b10000101101000000111101101011111 /
b10001110000001001110110010111001 .
b10001100100001110011010001101011 -
1$
1%
#250000
0%
#255000
b1011 E
0$
1%
#260000
0%
#265000
b1011 8
b11111011010100000110101000011111 ,
b1000111100110001010001111110100 =
b10001100100001110011010001101011 >
b10001110000001001110110010111001 ?
b1000111100110001010001111110100 @
b11111011110011110101101110001010 +
b1000011011010110010001111101000 :
b11100110010010010010110010110 ;
b110010110010100010110110001100 <
b1000011011010110010001111101000 A
b0 D
b1100011001010111101001111001 4
b110010110010100010110110001100 3
b11100110010010010010110010110 2
b1000011011010110010001111101000 1
b10000101101000000111101101011111 0
b10001110000001001110110010111001 /
b10001100100001110011010001101011 .
b1000111100110001010001111110100 -
1$
1%
#270000
0%
#275000
b1100 E
0$
1%
#280000
0%
#285000
b1100 8
b11110111001111101001010000110001 ,
b11110111000111111100010110101001 =
b1000111100110001010001111110100 >
b10001100100001110011010001101011 ?
b11110111000111111100010110101001 @
b10010000010100101001010101011111 +
b10000001011011111101011011101001 :
b1000011011010110010001111101000 ;
b11100110010010010010110010110 <
b10000001011011111101011011101001 A
b0 D
b110010110010100010110110001100 4
b11100110010010010010110010110 3
b1000011011010110010001111101000 2
b10000001011011111101011011101001 1
b10001110000001001110110010111001 0
b10001100100001110011010001101011 /
b1000111100110001010001111110100 .
b11110111000111111100010110101001 -
1$
1%
#290000
0%
#295000
b1101 E
0$
1%
#300000
0%
#305000
b1101 8
b11110001010111111101011010100011 ,
b10000111100100010010100110010000 =
b11110111000111111100010110101001 >
b1000111100110001010001111110100 ?
b10000111100100010010100110010000 @
b11100111110100110001010001110011 +
b11110010101111000001000011000 :
b10000001011011111101011011101001 ;
b1000011011010110010001111101000 <
b11110010101111000001000011000 A
b0 D
b11100110010010010010110010110 4
b1000011011010110010001111101000 3
b10000001011011111101011011101001 2
b11110010101111000001000011000 1
b10001100100001110011010001101011 0
b1000111100110001010001111110100 /
b11110111000111111100010110101001 .
b10000111100100010010100110010000 -
1$
1%
#310000
0%
#315000
b1110 E
0$
1%
#320000
0%
#325000
b1110 8
b11111100011010100001000111000110 ,
b11011001001100101110101100010110 =
b10000111100100010010100110010000 >
b11110111000111111100010110101001 ?
b11011001001100101110101100010110 @
b11000011111110100100111000011000 +
b1110100010110100100100011011110 :
b11110010101111000001000011000 ;
b10000001011011111101011011101001 <
b1110100010110100100100011011110 A
b0 D
b1000011011010110010001111101000 4
b10000001011011111101011011101001 3
b11110010101111000001000011000 2
b1110100010110100100100011011110 1
b1000111100110001010001111110100 0
b11110111000111111100010110101001 /
b10000111100100010010100110010000 .
b11011001001100101110101100010110 -
1$
1%
#330000
0%
#335000
b1111 E
0$
1%
#340000
0%
#345000
b1111 8
b10100000110000001101101101101010 ,
b11000000011001000101111111011110 =
b11011001001100101110101100010110 >
b10000111100100010010100110010000 ?
b11000000011001000101111111011110 @
b10000001110010100100000100100 +
b1011100100101111001000001100 :
b1110100010110100100100011011110 ;
b11110010101111000001000011000 <
b1011100100101111001000001100 A
b0 D
b10000001011011111101011011101001 4
b11110010101111000001000011000 3
b1110100010110100100100011011110 2
b1011100100101111001000001100 1
b11110111000111111100010110101001 0
b10000111100100010010100110010000 /
b11011001001100101110101100010110 .
b11000000011001000101111111011110 -
1$
b11000 #
b11000 )
1%
#350000
0%
#355000
b10000 E
0$
1%
#360000
0%
#365000
b10000 8
b101001001101111010000110001111 ,
b10110000111110100010001110001110 =
b11000000011001000101111111011110 >
b11011001001100101110101100010110 ?
b10110000111110100010001110001110 @
b11111000101000101111100100001100 +
b111010110010000110111001101 :
b1011100100101111001000001100 ;
b1110100010110100100100011011110 <
b111010110010000110111001101 A
b0 D
b11110010101111000001000011000 4
b1110100010110100100100011011110 3
b1011100100101111001000001100 2
b111010110010000110111001101 1
b10000111100100010010100110010000 0
b11011001001100101110101100010110 /
b11000000011001000101111111011110 .
b10110000111110100010001110001110 -
1$
b1100001011000100110001110000000 #
b1100001011000100110001110000000 )
1%
#370000
0%
#375000
b10001 E
0$
1%
#380000
0%
#385000
b10001 8
b10111101111111110000010010011 ,
b100001110110101001101010011011 =
b10110000111110100010001110001110 >
b11000000011001000101111111011110 ?
b100001110110101001101010011011 @
b10101011001110111111100100111110 +
b10000000001101000010001010011100 :
b111010110010000110111001101 ;
b1011100100101111001000001100 <
b10000000001101000010001010011100 A
b0 D
b1110100010110100100100011011110 4
b1011100100101111001000001100 3
b111010110010000110111001101 2
b10000000001101000010001010011100 1
b11011001001100101110101100010110 0
b11000000011001000101111111011110 /
b10110000111110100010001110001110 .
b100001110110101001101010011011 -
1$
b11110000000000000000 #
b11110000000000000000 )
1%
#390000
0%
#395000
b10010 E
0$
1%
#400000
0%
#405000
b10010 8
b11110010010100100100001000111100 ,
b11000010111110111101100111010001 =
b100001110110101001101010011011 >
b10110000111110100010001110001110 ?
b11000010111110111101100111010001 @
b1100001001010011100110000011 +
b10000100011011101110010001010100 :
b10000000001101000010001010011100 ;
b111010110010000110111001101 <
b10000100011011101110010001010100 A
b0 D
b1011100100101111001000001100 4
b111010110010000110111001101 3
b10000000001101000010001010011100 2
b10000100011011101110010001010100 1
b11000000011001000101111111011110 0
b10110000111110100010001110001110 /
b100001110110101001101010011011 .
b11000010111110111101100111010001 -
1$
b1111101101010000110010000000101 #
b1111101101010000110010000000101 )
1%
#410000
0%
#415000
b10011 E
0$
1%
#420000
0%
