expansion.v
/*
 * 模块名称：expansion
 *
 * 功能描述：
 *   本模块用于对输入的512位消息块进行SHA-256算法所需的消息扩展。
 *   采用16级流水线结构，每周期输出一个扩展后的消息字Wt。
 *
 * 扩展规则：
 *   1. 前16个字直接取自输入消息块
 *   2. 后48个字通过扩展算法生成：W[t] = σ1(W[t-2]) + W[t-7] + σ0(W[t-15]) + W[t-16]
 */

module expansion (
    input              clk,
    input              rst_n,
    input      [511:0] block_in,     // 512-bit input message block
    input              block_valid,  // 输入块有效信号
    output reg [ 31:0] Wt_out,       // 当前级的Wt输出
    output reg         Wt_valid      // Wt输出有效信号
);

  // =============================================
  // 内部信号定义
  // =============================================
  reg [31:0] W                                     [0:63];  // 消息调度数组
  reg [31:0] stage_reg                             [0:15];  // 16级流水线寄存器
  reg [ 6:0] t_counter;  // 扩展计数器 (0-63)
  reg        active;  // 扩展过程激活标志

  // =============================================
  // σ0和σ1函数定义
  // =============================================
  function [31:0] sigma0;
    input [31:0] x;
    sigma0 = {x[6:0], x[31:7]} ^ {x[17:0], x[31:18]} ^ (x >> 3);
  endfunction

  function [31:0] sigma1;
    input [31:0] x;
    sigma1 = {x[16:0], x[31:17]} ^ {x[18:0], x[31:19]} ^ (x >> 10);
  endfunction

  // =============================================
  // 主处理逻辑
  // =============================================
  always @(posedge clk or negedge rst_n) begin
    if (!rst_n) begin
      // 复位所有寄存器
      for (integer i = 0; i < 64; i++) W[i] <= 0;
      for (integer i = 0; i < 16; i++) stage_reg[i] <= 0;
      t_counter <= 0;
      active <= 0;
      Wt_out <= 0;
      Wt_valid <= 0;
    end else begin
      // 默认输出无效
      Wt_valid <= 0;

      if (block_valid && !active) begin
        // 新块到达，初始化前16个字
        for (integer t = 0; t < 16; t++) begin
          W[t] <= block_in[511-32*t-:32];
          stage_reg[t] <= 32'hFFFFFFFF;
        end
        t_counter <= 16;  // 从第16个字开始扩展
        active <= 1;
      end else if (active) begin
        // 扩展处理阶段
        if (t_counter < 96) begin
          // 计算新的Wt
          if (t_counter < 64) begin
            W[t_counter] <= sigma1(W[t_counter-2]) + W[t_counter-7] + sigma0(W[t_counter-15]) +
                W[t_counter-16];
          end

          // 更新流水线寄存器
          for (integer i = 0; i < 15; i++) begin
            stage_reg[i] <= stage_reg[i+1];
          end
          if (t_counter < 80) begin
            stage_reg[15] <= W[t_counter-16];  // 延迟16周期
          end else begin
            stage_reg[15] <= 0;  // 超出范围时清零
          end

          // 输出当前Wt
          if (t_counter >= 32) begin
            Wt_out   <= stage_reg[0];
            Wt_valid <= 1;
          end

          t_counter <= t_counter + 1;
        end else begin
          // 扩展完成
          active   <= 0;
          Wt_valid <= 0;
        end
      end
    end
  end

endmodule

expansion_tb.v
`timescale 1ns / 1ps

module expansion_tb ();

  // 时钟和复位信号
  reg clk;
  reg rst_n;

  // 模块输入
  reg [511:0] block_in;
  reg block_valid;

  // 模块输出
  wire [31:0] Wt_out;
  wire Wt_valid;

  // 用于收集Wt值的数组
  reg [31:0] W[0:63];
  reg [511:0] block2;

  // 收集所有64个Wt值
  integer t;
  // 收集第一个块的Wt值
  integer block1_count;
  // 收集第二个块的Wt值
  integer block2_count;

  // 实例化被测模块
  expansion uut (
      .clk(clk),
      .rst_n(rst_n),
      .block_in(block_in),
      .block_valid(block_valid),
      .Wt_out(Wt_out),
      .Wt_valid(Wt_valid)
  );

  // 时钟生成（周期10ns）
  initial begin
    clk = 0;
    forever #5 clk = ~clk;
  end

  // 测试过程
  initial begin
    // =============================================
    // 测试用例1：基本功能测试 - 验证前16个字直接输出
    // =============================================
    $display("\n[TEST CASE 1] Basic functionality test - first 16 words");

    // 初始化
    #20;
    rst_n = 0;
    block_in = 0;
    block_valid = 0;
    #10;

    // 释放复位
    rst_n = 1;
    #10;

    // 准备测试数据块 (前16个字设置为0-15)
    for (integer i = 0; i < 16; i = i + 1) begin
      block_in[511-32*i-:32] = i;
    end

    // 发送有效块
    @(posedge clk);
    block_valid = 1;
    @(posedge clk);
    block_valid = 0;

    // 等待16个周期的流水线延迟
    repeat (16) @(posedge clk);

    // 检查前16个输出
    for (integer t = 0; t < 16; t = t + 1) begin
      wait (Wt_valid);
      #0.1;  // 确保输出稳定
      $display("W[%0d] = %h", t, Wt_out);

      if (Wt_out !== t) begin
        $display("[RESULT] FAIL: W[%0d] expected %h, got %h", t, t, Wt_out);
      end else begin
        $display("[RESULT] PASS: W[%0d] correct", t);
      end

      @(posedge clk);
    end

    // =============================================
    // 测试用例2：扩展功能测试 - 验证后48个字的生成
    // =============================================
    $display("\n[TEST CASE 2] Expansion test - verify words 16-63");

    // 等待当前扩展完成
    while (Wt_valid) @(posedge clk);
    #10;

    // 准备新的测试数据块 (使用SHA-256标准测试向量)
    block_in = 512'h61626380000000000000000000000000000000000000000000000000000000000000000000000000000000000000000000000000000000000000000000000018;

    // 发送有效块
    @(posedge clk);
    block_valid = 1;
    @(posedge clk);
    block_valid = 0;

    t = 0;
    while (t < 64) begin
      if (Wt_valid) begin
        W[t] = Wt_out;
        $display("W[%0d] = %h", t, Wt_out);
        t = t + 1;
      end
      @(posedge clk);
    end

    // 验证扩展结果 (对比预计算的SHA-256扩展值)
    // 注意：这里只验证部分关键点，实际测试中应验证所有64个字

    // 验证W[16] (第一个扩展字)
    if (W[16] === 32'h61626380) begin
      $display("[RESULT] PASS: W[16] correct");
    end else begin
      $display("[RESULT] FAIL: W[16] expected 61626380, got %h", W[16]);
    end

    // 验证W[17] (第二个扩展字)
    if (W[17] === 32'h000f0000) begin
      $display("[RESULT] PASS: W[17] correct");
    end else begin
      $display("[RESULT] FAIL: W[17] expected 000f0000, got %h", W[17]);
    end

    // 验证W[18] (第三个扩展字)
    if (W[18] === 32'h7da86405) begin
      $display("[RESULT] PASS: W[18] correct");
    end else begin
      $display("[RESULT] FAIL: W[18] expected 7da86405, got %h", W[18]);
    end

    // 验证W[63] (最后一个扩展字)
    if (W[63] === 32'h12b1edeb) begin
      $display("[RESULT] PASS: W[63] correct");
    end else begin
      $display("[RESULT] FAIL: W[63] expected 12b1edeb, got %h", W[63]);
    end

    // =============================================
    // 测试用例3：流水线功能测试 - 验证连续块处理
    // =============================================
    // $display("\n[TEST CASE 3] Pipeline test - verify continuous block processing");

    // // 发送第一个块
    // @(posedge clk);
    // block_valid = 1;
    // block_in = 512'h000102030405060708090a0b0c0d0e0f101112131415161718191a1b1c1d1e1f202122232425262728292a2b2c2d2e2f303132333435363738393a3b3c3d3e3f;
    // @(posedge clk);
    // block_valid = 0;

    // // 在第一个块处理过程中发送第二个块
    // #100;  // 等待部分处理完成
    // @(posedge clk);
    // block_valid = 1;
    // block_in = 512'h404142434445464748494a4b4c4d4e4f505152535455565758595a5b5c5d5e5f606162636465666768696a6b6c6d6e6f707172737475767778797a7b7c7d7e7f;
    // @(posedge clk);
    // block_valid  = 0;

    // block1_count = 0;
    // while (block1_count < 64) begin
    //   if (Wt_valid) begin
    //     $display("Block1 W[%0d] = %h", block1_count, Wt_out);
    //     block1_count = block1_count + 1;
    //   end
    //   @(posedge clk);
    // end

    // block2_count = 0;
    // while (block2_count < 64) begin
    //   if (Wt_valid) begin
    //     $display("Block2 W[%0d] = %h", block2_count, Wt_out);
    //     block2_count = block2_count + 1;
    //   end
    //   @(posedge clk);
    // end

    // // 验证第二个块的第一个字是否正确
    // if (Wt_out === 32'h40414243) begin
    //   $display("[RESULT] PASS: Second block processing started correctly");
    // end else begin
    //   $display("[RESULT] FAIL: Second block first word expected 40414243, got %h", Wt_out);
    // end

    // =============================================
    // 结束仿真
    // =============================================
    #1000;
    $display("\n[SIMULATION FINISHED]");
    $finish;
  end

  // 波形转储
  initial begin
    $dumpfile("expansion.vcd");
    $dumpvars(0, expansion_tb);
  end

endmodule

expansion.vcd
$date
	Mon Jul 28 16:16:29 2025
$end
$version
	Icarus Verilog
$end
$timescale
	1ps
$end
$scope module expansion_tb $end
$var wire 1 ! Wt_valid $end
$var wire 32 " Wt_out [31:0] $end
$var reg 512 # block_in [511:0] $end
$var reg 1 $ block_valid $end
$var reg 1 % clk $end
$var reg 1 & rst_n $end
$var integer 32 ' t [31:0] $end
$scope module uut $end
$var wire 512 ( block_in [511:0] $end
$var wire 1 $ block_valid $end
$var wire 1 % clk $end
$var wire 1 & rst_n $end
$var reg 32 ) Wt_out [31:0] $end
$var reg 1 ! Wt_valid $end
$var reg 1 * active $end
$var reg 7 + t_counter [6:0] $end
$scope function sigma0 $end
$var reg 32 , x [31:0] $end
$upscope $end
$scope function sigma1 $end
$var reg 32 - x [31:0] $end
$upscope $end
$scope begin $ivl_for_loop0 $end
$var integer 32 . i [31:0] $end
$upscope $end
$scope begin $ivl_for_loop1 $end
$var integer 32 / i [31:0] $end
$upscope $end
$scope begin $ivl_for_loop2 $end
$var integer 32 0 t [31:0] $end
$upscope $end
$scope begin $ivl_for_loop3 $end
$var integer 32 1 i [31:0] $end
$upscope $end
$upscope $end
$scope begin $ivl_for_loop4 $end
$var integer 32 2 i [31:0] $end
$upscope $end
$scope begin $ivl_for_loop5 $end
$var integer 32 3 t [31:0] $end
$upscope $end
$upscope $end
$enddefinitions $end
$comment Show the parameter values. $end
$dumpall
$end
#0
$dumpvars
bx 3
bx 2
bx 1
bx 0
bx /
bx .
bx -
bx ,
bx +
x*
bx )
bx (
bx '
x&
0%
x$
bx #
bx "
x!
$end
#5000
0!
1%
#10000
0%
#15000
1%
#20000
b0 "
b0 )
0*
b0 +
b10000 /
b1000000 .
0%
0$
b0 #
b0 (
0&
#25000
b10000 /
b1000000 .
1%
#30000
0%
1&
#35000
1%
#40000
0%
b10000000000000000000000000000001000000000000000000000000000000011000000000000000000000000000001000000000000000000000000000000010100000000000000000000000000000110000000000000000000000000000001110000000000000000000000000000100000000000000000000000000000001001000000000000000000000000000010100000000000000000000000000000101100000000000000000000000000001100000000000000000000000000000011010000000000000000000000000000111000000000000000000000000000001111 #
b10000000000000000000000000000001000000000000000000000000000000011000000000000000000000000000001000000000000000000000000000000010100000000000000000000000000000110000000000000000000000000000001110000000000000000000000000000100000000000000000000000000000001001000000000000000000000000000010100000000000000000000000000000101100000000000000000000000000001100000000000000000000000000000011010000000000000000000000000000111000000000000000000000000000001111 (
b10000 2
#45000
1*
b10000 +
b10000 0
1$
1%
#50000
0%
#55000
b10001 +
b1111 1
b1 ,
b1110 -
0$
1%
#60000
0%
#65000
b10010 +
b1111 1
b10 ,
b1111 -
1%
#70000
0%
#75000
b10011 +
b1111 1
b11 ,
b10000001110000000000001001 -
1%
#80000
0%
#85000
b10100 +
b1111 1
b100 ,
b100000001101110000000001011 -
1%
#90000
0%
#95000
b10101 +
b1111 1
b101 ,
b1100110000001011110000010010000 -
1%
#100000
0%
#105000
b10110 +
b1111 1
b110 ,
b10110100000001101110001101001010 -
1%
#110000
0%
#115000
b10111 +
b1111 1
b111 ,
b1010110010001001111111011001011 -
1%
#120000
0%
#125000
b11000 +
b1111 1
b1000 ,
b10111001111000101000110101001110 -
1%
#130000
0%
#135000
b11001 +
b1111 1
b1001 ,
b11101110101010110001000011101010 -
1%
#140000
0%
#145000
b11010 +
b1111 1
b1010 ,
b101001001010011111001101111111 -
1%
#150000
0%
#155000
b11011 +
b1111 1
b1011 ,
b10111001010000001011000 -
1%
#160000
0%
#165000
b11100 +
b1111 1
b1100 ,
b1000001111000101001110001100111 -
1%
#170000
0%
#175000
b11101 +
b1111 1
b1101 ,
b10001110001100001011101001100010 -
1%
#180000
0%
#185000
b11110 +
b1111 1
b1110 ,
b10001011111101110010111101000001 -
1%
#190000
0%
#195000
b11111 +
b1111 1
b1111 ,
b11110010001000110100001001011 -
1%
#200000
0%
#205000
b100000 +
b1111 1
b10000001110000000000001001 ,
b1111101000110001001101001000110 -
1%
#210000
0%
#215000
b100001 +
1!
b1111 1
b100000001101110000000001011 ,
b10110010011000101111110 -
b0 3
1%
#220000
0%
#225000
b100010 +
b1 "
b1 )
1!
b1111 1
b1100110000001011110000010010000 ,
b110001000110000000010111110000 -
b1 3
1%
#230000
0%
#235000
b100011 +
b10 "
b10 )
1!
b1111 1
b10110100000001101110001101001010 ,
b10110001000001001000001110011011 -
b10 3
1%
#240000
0%
#245000
b100100 +
b11 "
b11 )
1!
b1111 1
b1010110010001001111111011001011 ,
b11101000101010101010000101101101 -
b11 3
1%
#250000
0%
#255000
b100101 +
b100 "
b100 )
1!
b1111 1
b10111001111000101000110101001110 ,
b11111110110010100111110000000001 -
b100 3
1%
#260000
0%
#265000
b100110 +
b101 "
b101 )
1!
b1111 1
b11101110101010110001000011101010 ,
b1111010110000110111001100110010 -
b101 3
1%
#270000
0%
#275000
b100111 +
b110 "
b110 )
1!
b1111 1
b101001001010011111001101111111 ,
b1101110001110010100010111111111 -
b110 3
1%
#280000
0%
#285000
b101000 +
b111 "
b111 )
1!
b1111 1
b10111001010000001011000 ,
b10011110010100000001000101000111 -
b111 3
1%
#290000
0%
#295000
b101001 +
b1000 "
b1000 )
1!
b1111 1
b1000001111000101001110001100111 ,
b110001110001111001001100100111 -
b1000 3
1%
#300000
0%
#305000
b101010 +
b1001 "
b1001 )
1!
b1111 1
b10001110001100001011101001100010 ,
b1111100111110000100110101011100 -
b1001 3
1%
#310000
0%
#315000
b101011 +
b1010 "
b1010 )
1!
b1111 1
b10001011111101110010111101000001 ,
b10000110101010001001011111010000 -
b1010 3
1%
#320000
0%
#325000
b101100 +
b1011 "
b1011 )
1!
b1111 1
b11110010001000110100001001011 ,
b1101010000010100111111000001100 -
b1011 3
1%
#330000
0%
#335000
b101101 +
b1100 "
b1100 )
1!
b1111 1
b1111101000110001001101001000110 ,
b10111011111000011001000010000011 -
b1100 3
1%
#340000
0%
#345000
b101110 +
b1101 "
b1101 )
1!
b1111 1
b10110010011000101111110 ,
b11111010111101000111001001100011 -
b1101 3
1%
#350000
0%
#355000
b101111 +
b1110 "
b1110 )
1!
b1111 1
b110001000110000000010111110000 ,
b1011100110111001000100110110100 -
b1110 3
1%
#360000
0%
#365000
b110000 +
b1111 "
b1111 )
1!
b1111 1
b10110001000001001000001110011011 ,
b10110011101111000000100000000 -
b1111 3
1%
#370000
0%
#375000
b110001 +
b10000001110000000000001001 "
b10000001110000000000001001 )
1!
b1111 1
b11101000101010101010000101101101 ,
b111010100010100100111010100100 -
b10000 3
1%
#380000
0%
#385000
b110010 +
b100000001101110000000001011 "
b100000001101110000000001011 )
1!
b1111 1
b11111110110010100111110000000001 ,
b11101010000010101010011100001010 -
1%
#390000
0%
#395000
b110011 +
b1100110000001011110000010010000 "
b1100110000001011110000010010000 )
1!
b1111 1
b1111010110000110111001100110010 ,
b11111000001101101011010101110011 -
1%
#400000
0%
#405000
b110100 +
b10110100000001101110001101001010 "
b10110100000001101110001101001010 )
1!
b1111 1
b1101110001110010100010111111111 ,
b101111000011111000000110100111 -
1%
#410000
0%
#415000
b110101 +
b1010110010001001111111011001011 "
b1010110010001001111111011001011 )
1!
b1111 1
b10011110010100000001000101000111 ,
b111101010010011111001101000100 -
1%
#420000
0%
#425000
b110110 +
b10111001111000101000110101001110 "
b10111001111000101000110101001110 )
1!
b1111 1
b110001110001111001001100100111 ,
b10101010111100010011000000100110 -
1%
#430000
0%
#435000
b110111 +
b11101110101010110001000011101010 "
b11101110101010110001000011101010 )
1!
b1111 1
b1111100111110000100110101011100 ,
b11100101000111011101100000001110 -
1%
#440000
0%
#445000
b111000 +
b101001001010011111001101111111 "
b101001001010011111001101111111 )
1!
b1111 1
b10000110101010001001011111010000 ,
b1000011101010100100110110001000 -
1%
#450000
0%
#455000
b111001 +
b10111001010000001011000 "
b10111001010000001011000 )
1!
b1111 1
b1101010000010100111111000001100 ,
b10111010001000000100110011011 -
1%
#460000
0%
#465000
b111010 +
b1000001111000101001110001100111 "
b1000001111000101001110001100111 )
1!
b1111 1
b10111011111000011001000010000011 ,
b1111000110000010010100010000001 -
1%
#470000
0%
#475000
b111011 +
b10001110001100001011101001100010 "
b10001110001100001011101001100010 )
1!
b1111 1
b11111010111101000111001001100011 ,
b11000101110010011001001101111110 -
1%
#480000
0%
#485000
b111100 +
b10001011111101110010111101000001 "
b10001011111101110010111101000001 )
1!
b1111 1
b1011100110111001000100110110100 ,
b11001100110011100011010001001011 -
1%
#490000
0%
#495000
b111101 +
b11110010001000110100001001011 "
b11110010001000110100001001011 )
1!
b1111 1
b10110011101111000000100000000 ,
b100110111010000010000011110111 -
1%
#500000
0%
#505000
b111110 +
b1111101000110001001101001000110 "
b1111101000110001001101001000110 )
1!
b1111 1
b111010100010100100111010100100 ,
b11111110000000010011010111110110 -
1%
#510000
0%
#515000
b111111 +
b10110010011000101111110 "
b10110010011000101111110 )
1!
b1111 1
b11101010000010101010011100001010 ,
b10010111100101011011111110011100 -
1%
#520000
0%
#525000
b1000000 +
b110001000110000000010111110000 "
b110001000110000000010111110000 )
1!
b1111 1
b11111000001101101011010101110011 ,
b11000110110000101111111100010011 -
1%
#530000
0%
#535000
b1000001 +
b10110001000001001000001110011011 "
b10110001000001001000001110011011 )
1!
b1111 1
1%
#540000
0%
#545000
b1000010 +
b11101000101010101010000101101101 "
b11101000101010101010000101101101 )
1!
b1111 1
1%
#550000
0%
#555000
b1000011 +
b11111110110010100111110000000001 "
b11111110110010100111110000000001 )
1!
b1111 1
1%
#560000
0%
#565000
b1000100 +
b1111010110000110111001100110010 "
b1111010110000110111001100110010 )
1!
b1111 1
1%
#570000
0%
#575000
b1000101 +
b1101110001110010100010111111111 "
b1101110001110010100010111111111 )
1!
b1111 1
1%
#580000
0%
#585000
b1000110 +
b10011110010100000001000101000111 "
b10011110010100000001000101000111 )
1!
b1111 1
1%
#590000
0%
#595000
b1000111 +
b110001110001111001001100100111 "
b110001110001111001001100100111 )
1!
b1111 1
1%
#600000
0%
#605000
b1001000 +
b1111100111110000100110101011100 "
b1111100111110000100110101011100 )
1!
b1111 1
1%
#610000
0%
#615000
b1001001 +
b10000110101010001001011111010000 "
b10000110101010001001011111010000 )
1!
b1111 1
1%
#620000
0%
#625000
b1001010 +
b1101010000010100111111000001100 "
b1101010000010100111111000001100 )
1!
b1111 1
1%
#630000
0%
#635000
b1001011 +
b10111011111000011001000010000011 "
b10111011111000011001000010000011 )
1!
b1111 1
1%
#640000
0%
#645000
b1001100 +
b11111010111101000111001001100011 "
b11111010111101000111001001100011 )
1!
b1111 1
1%
#650000
0%
#655000
b1001101 +
b1011100110111001000100110110100 "
b1011100110111001000100110110100 )
1!
b1111 1
1%
#660000
0%
#665000
b1001110 +
b10110011101111000000100000000 "
b10110011101111000000100000000 )
1!
b1111 1
1%
#670000
0%
#675000
b1001111 +
b111010100010100100111010100100 "
b111010100010100100111010100100 )
1!
b1111 1
1%
#680000
0%
#685000
b1010000 +
b11101010000010101010011100001010 "
b11101010000010101010011100001010 )
1!
b1111 1
1%
#690000
0%
#695000
b1010001 +
b11111000001101101011010101110011 "
b11111000001101101011010101110011 )
1!
b1111 1
1%
#700000
0%
#705000
b1010010 +
b101111000011111000000110100111 "
b101111000011111000000110100111 )
1!
b1111 1
1%
#710000
0%
#715000
b1010011 +
b111101010010011111001101000100 "
b111101010010011111001101000100 )
1!
b1111 1
1%
#720000
0%
#725000
b1010100 +
b10101010111100010011000000100110 "
b10101010111100010011000000100110 )
1!
b1111 1
1%
#730000
0%
#735000
b1010101 +
b11100101000111011101100000001110 "
b11100101000111011101100000001110 )
1!
b1111 1
1%
#740000
0%
#745000
b1010110 +
b1000011101010100100110110001000 "
b1000011101010100100110110001000 )
1!
b1111 1
1%
#750000
0%
#755000
b1010111 +
b10111010001000000100110011011 "
b10111010001000000100110011011 )
1!
b1111 1
1%
#760000
0%
#765000
b1011000 +
b1111000110000010010100010000001 "
b1111000110000010010100010000001 )
1!
b1111 1
1%
#770000
0%
#775000
b1011001 +
b11000101110010011001001101111110 "
b11000101110010011001001101111110 )
1!
b1111 1
1%
#780000
0%
#785000
b1011010 +
b11001100110011100011010001001011 "
b11001100110011100011010001001011 )
1!
b1111 1
1%
#790000
0%
#795000
b1011011 +
b100110111010000010000011110111 "
b100110111010000010000011110111 )
1!
b1111 1
1%
#800000
0%
#805000
b1011100 +
b11111110000000010011010111110110 "
b11111110000000010011010111110110 )
1!
b1111 1
1%
#810000
0%
#815000
b1011101 +
b10010111100101011011111110011100 "
b10010111100101011011111110011100 )
1!
b1111 1
1%
#820000
0%
#825000
b1011110 +
b11000110110000101111111100010011 "
b11000110110000101111111100010011 )
1!
b1111 1
1%
#830000
0%
#835000
b1011111 +
b10111100101110111010111010101001 "
b10111100101110111010111010101001 )
1!
b1111 1
1%
#840000
0%
#845000
b1100000 +
b100101110110001010101101010111 "
b100101110110001010101101010111 )
1!
b1111 1
1%
#850000
0%
#855000
0*
0!
1%
#860000
0%
#865000
1%
#870000
0%
#875000
1*
b10000 +
b10000 0
1$
1%
b1100001011000100110001110000000000000000000000000000000000000000000000000000000000000000000000000000000000000000000000000000000000000000000000000000000000000000000000000000000000000000000000000000000000000000000000000000000000000000000000000000000000000000000000000000000000000000000000000000000000000000000000000000000000000000000000000000000000000000000000000000000000000000000000000000000000000000000000000000000000000000000000000000000000000000000000000000000000000000000000000000000000000000000000000011000 #
b1100001011000100110001110000000000000000000000000000000000000000000000000000000000000000000000000000000000000000000000000000000000000000000000000000000000000000000000000000000000000000000000000000000000000000000000000000000000000000000000000000000000000000000000000000000000000000000000000000000000000000000000000000000000000000000000000000000000000000000000000000000000000000000000000000000000000000000000000000000000000000000000000000000000000000000000000000000000000000000000000000000000000000000000000011000 (
#880000
0%
#885000
b10001 +
b1111 1
b0 ,
b0 -
b0 '
0$
1%
#890000
0%
#895000
b10010 +
b1111 1
b11000 -
1%
#900000
0%
#905000
b10011 +
b1111 1
b1100001011000100110001110000000 -
1%
#910000
0%
#915000
b10100 +
b1111 1
b11110000000000000000 -
1%
#920000
0%
#925000
b10101 +
b1111 1
b1111101101010000110010000000101 -
1%
#930000
0%
#935000
b10110 +
b1111 1
b1100000000000000000001111000110 -
1%
#940000
0%
#945000
b10111 +
b1111 1
b111110100111010111101101111000 -
1%
#950000
0%
#955000
b11000 +
b1111 1
b1100000111111110000000000 -
1%
#960000
0%
#965000
b11001 +
b1111 1
b10010110111001011111111011011 -
1%
#970000
0%
#975000
b11010 +
b1111 1
b11100010111000101100001110001110 -
1%
#980000
0%
#985000
b11011 +
b1111 1
b11001000001000010101110000011010 -
1%
#990000
0%
#995000
b11100 +
b1111 1
b10110111001101100111100110100010 -
1%
#1000000
0%
#1005000
b11101 +
b1111 1
b11100101101111000011100100001001 -
1%
#1010000
0%
#1015000
b11110 +
b1111 1
b110010011001100011110001011011 -
1%
#1020000
0%
#1025000
b11111 +
b1111 1
b11000 ,
b10011101001000001001110101100111 -
1%
#1030000
0%
#1035000
b100000 +
b1111 1
b1100001011000100110001110000000 ,
b11101100100001110010011011001011 -
1%
#1040000
0%
#1045000
b100001 +
1!
b1100001011000100110001110000000 "
b1100001011000100110001110000000 )
b1111 1
b11110000000000000000 ,
b1110000001000010011100010100100 -
1%
#1050000
0%
#1055000
b100010 +
b0 "
b0 )
1!
b1111 1
b1111101101010000110010000000101 ,
b11010011101101111001011100111011 -
b1 '
1%
#1060000
0%
#1065000
b100011 +
1!
b1111 1
b1100000000000000000001111000110 ,
b10010011111101011001100101111111 -
b10 '
1%
#1070000
0%
#1075000
b100100 +
1!
b1111 1
b111110100111010111101101111000 ,
b111011011010001011101001110011 -
b11 '
1%
#1080000
0%
#1085000
b100101 +
1!
b1111 1
b1100000111111110000000000 ,
b10101111111101001111111111000001 -
b100 '
1%
#1090000
0%
#1095000
b100110 +
1!
b1111 1
b10010110111001011111111011011 ,
b11110001000010100101110001100010 -
b101 '
1%
#1100000
0%
#1105000
b100111 +
1!
b1111 1
b11100010111000101100001110001110 ,
b1010100010110011100110010110 -
b110 '
1%
#1110000
0%
#1115000
b101000 +
1!
b1111 1
b11001000001000010101110000011010 ,
b1110010101011111000001100001010 -
b111 '
1%
#1120000
0%
#1125000
b101001 +
1!
b1111 1
b10110111001101100111100110100010 ,
b10010100000010011110001100111110 -
b1000 '
1%
#1130000
0%
#1135000
b101010 +
1!
b1111 1
b11100101101111000011100100001001 ,
b100100011001000001010100100010 -
b1001 '
1%
#1140000
0%
#1145000
b101011 +
1!
b1111 1
b110010011001100011110001011011 ,
b10011111010001111011111110010100 -
b1010 '
1%
#1150000
0%
#1155000
b101100 +
1!
b1111 1
b10011101001000001001110101100111 ,
b11110000101001100100111101011010 -
b1011 '
1%
#1160000
0%
#1165000
b101101 +
1!
b1111 1
b11101100100001110010011011001011 ,
b111110001001000110101001111001 -
b1100 '
1%
#1170000
0%
#1175000
b101110 +
1!
b1111 1
b1110000001000010011100010100100 ,
b100111001100110011101110100011 -
b1101 '
1%
#1180000
0%
#1185000
b101111 +
1!
b1111 1
b11010011101101111001011100111011 ,
b1100010001110110001111110010 -
b1110 '
1%
#1190000
0%
#1195000
b110000 +
b11000 "
b11000 )
1!
b1111 1
b10010011111101011001100101111111 ,
b10000100000010101011111100100111 -
b1111 '
1%
#1200000
0%
#1205000
b110001 +
b1100001011000100110001110000000 "
b1100001011000100110001110000000 )
1!
b1111 1
b111011011010001011101001110011 ,
b1111010001010010000110101011101 -
b10000 '
1%
#1210000
0%
#1215000
b110010 +
b11110000000000000000 "
b11110000000000000000 )
1!
b1111 1
b10101111111101001111111111000001 ,
b110010111000100001111011010 -
b10001 '
1%
#1220000
0%
#1225000
b110011 +
b1111101101010000110010000000101 "
b1111101101010000110010000000101 )
1!
b1111 1
b11110001000010100101110001100010 ,
b11111011001111101000100111001011 -
b10010 '
1%
#1230000
0%
#1235000
b110100 +
b1100000000000000000001111000110 "
b1100000000000000000001111000110 )
1!
b1111 1
b1010100010110011100110010110 ,
b11001100011101100001011111011011 -
b10011 '
1%
#1240000
0%
#1245000
b110101 +
b111110100111010111101101111000 "
b111110100111010111101101111000 )
1!
b1111 1
b1110010101011111000001100001010 ,
b10111001111001100110110000110100 -
b10100 '
1%
#1250000
0%
#1255000
b110110 +
b1100000111111110000000000 "
b1100000111111110000000000 )
1!
b1111 1
b10010100000010011110001100111110 ,
b10101001100110010011011001100111 -
b10101 '
1%
#1260000
0%
#1265000
b110111 +
b10010110111001011111111011011 "
b10010110111001011111111011011 )
1!
b1111 1
b100100011001000001010100100010 ,
b10000100101110101101111011011101 -
b10110 '
1%
#1270000
0%
#1275000
b111000 +
b11100010111000101100001110001110 "
b11100010111000101100001110001110 )
1!
b1111 1
b10011111010001111011111110010100 ,
b11000010000101000110001010111100 -
b10111 '
1%
#1280000
0%
#1285000
b111001 +
b11001000001000010101110000011010 "
b11001000001000010101110000011010 )
1!
b1111 1
b11110000101001100100111101011010 ,
b10100100001110100011100101100 -
b11000 '
1%
#1290000
0%
#1295000
b111010 +
b10110111001101100111100110100010 "
b10110111001101100111100110100010 )
1!
b1111 1
b111110001001000110101001111001 ,
b10110010000011110111101010011001 -
b11001 '
1%
#1300000
0%
#1305000
b111011 +
b11100101101111000011100100001001 "
b11100101101111000011100100001001 )
1!
b1111 1
b100111001100110011101110100011 ,
b11101111010101111011100111001101 -
b11010 '
1%
#1310000
0%
#1315000
b111100 +
b110010011001100011110001011011 "
b110010011001100011110001011011 )
1!
b1111 1
b1100010001110110001111110010 ,
b11101011111001101011001000111000 -
b11011 '
1%
#1320000
0%
#1325000
b111101 +
b10011101001000001001110101100111 "
b10011101001000001001110101100111 )
1!
b1111 1
b10000100000010101011111100100111 ,
b10011111111000110000100101011110 -
b11100 '
1%
#1330000
0%
#1335000
b111110 +
b11101100100001110010011011001011 "
b11101100100001110010011011001011 )
1!
b1111 1
b1111010001010010000110101011101 ,
b1111000101111001000110101001011 -
b11101 '
1%
#1340000
0%
#1345000
b111111 +
b1110000001000010011100010100100 "
b1110000001000010011100010100100 )
1!
b1111 1
b110010111000100001111011010 ,
b10100100001111111100111100010101 -
b11110 '
1%
#1350000
0%
#1355000
b1000000 +
b11010011101101111001011100111011 "
b11010011101101111001011100111011 )
1!
b1111 1
b11111011001111101000100111001011 ,
b1100110100010110010111111111000 -
b11111 '
1%
#1360000
0%
#1365000
b1000001 +
b10010011111101011001100101111111 "
b10010011111101011001100101111111 )
1!
b1111 1
b100000 '
1%
#1370000
0%
#1375000
b1000010 +
b111011011010001011101001110011 "
b111011011010001011101001110011 )
1!
b1111 1
b100001 '
1%
#1380000
0%
#1385000
b1000011 +
b10101111111101001111111111000001 "
b10101111111101001111111111000001 )
1!
b1111 1
b100010 '
1%
#1390000
0%
#1395000
b1000100 +
b11110001000010100101110001100010 "
b11110001000010100101110001100010 )
1!
b1111 1
b100011 '
1%
#1400000
0%
#1405000
b1000101 +
b1010100010110011100110010110 "
b1010100010110011100110010110 )
1!
b1111 1
b100100 '
1%
#1410000
0%
#1415000
b1000110 +
b1110010101011111000001100001010 "
b1110010101011111000001100001010 )
1!
b1111 1
b100101 '
1%
#1420000
0%
#1425000
b1000111 +
b10010100000010011110001100111110 "
b10010100000010011110001100111110 )
1!
b1111 1
b100110 '
1%
#1430000
0%
#1435000
b1001000 +
b100100011001000001010100100010 "
b100100011001000001010100100010 )
1!
b1111 1
b100111 '
1%
#1440000
0%
#1445000
b1001001 +
b10011111010001111011111110010100 "
b10011111010001111011111110010100 )
1!
b1111 1
b101000 '
1%
#1450000
0%
#1455000
b1001010 +
b11110000101001100100111101011010 "
b11110000101001100100111101011010 )
1!
b1111 1
b101001 '
1%
#1460000
0%
#1465000
b1001011 +
b111110001001000110101001111001 "
b111110001001000110101001111001 )
1!
b1111 1
b101010 '
1%
#1470000
0%
#1475000
b1001100 +
b100111001100110011101110100011 "
b100111001100110011101110100011 )
1!
b1111 1
b101011 '
1%
#1480000
0%
