padding.v
/*
 * 模块名称：padding
 *
 * 功能描述：
 *   本模块用于对输入的任意长度消息进行SHA-256算法所需的预处理（填充）。
 *   输入为按字节输入的消息及其有效信号，输出为填充后的512位数据块及块有效信号。
 *
 * 填充规则：
 *   1. 在消息末尾附加一个"1"比特（即10000000）。
 *   2. 补"0"直到消息长度满足 ≡ 448 mod 512（即剩余64位）。
 *   3. 最后补充64位，表示原始消息的位长度（采用大端序）。
 */

module padding (
    input              clk,
    input              rst_n,
    input      [  7:0] data_in,         // 输入消息字节
    input              data_in_valid,   // 输入消息有效信号
    input              data_last,       // 输入消息最后一个字节标志
    output reg [511:0] data_out,        // 输出填充后的512位数据块
    output reg         data_out_valid,  // 输出数据块有效信号
    output reg         ready            // 模块就绪信号（可接收新输入）
);

  // =============================================
  // 状态定义
  // =============================================
  localparam IDLE = 3'b000;  // 等待输入
  localparam RECEIVE = 3'b001;  // 接收输入
  localparam PAD_1 = 3'b010;  // 补1
  localparam PAD_0 = 3'b011;  // 补0
  localparam PAD_LEN = 3'b100;  // 补长度
  localparam OUTPUT = 3'b101;  // 输出数据块
  localparam SECOND_BLOCK = 3'b110;  // 处理第二个数据块

  // =============================================
  // 内部寄存器
  // =============================================
  reg [  2:0] state;
  reg [ 63:0] msg_length;  // 原始消息长度（位）
  reg [  5:0] byte_count;  // 当前块内字节计数（0-63）
  reg [511:0] temp_block;  // 临时存储块数据
  reg [  5:0] fill_pos;  // 填充位置指针
  reg         needs_second_block;  // 需要第二个块标志

  // =============================================
  // 主状态机逻辑
  // =============================================
  always @(posedge clk or negedge rst_n) begin
    if (!rst_n) begin
      // 复位所有寄存器
      state              <= IDLE;
      msg_length         <= 0;
      byte_count         <= 0;
      temp_block         <= 0;
      data_out           <= 0;
      data_out_valid     <= 0;
      ready              <= 0;
      fill_pos           <= 0;
      needs_second_block <= 0;
    end else begin
      // 输出状态默认无效
      data_out_valid <= 0;

      case (state)
        IDLE: begin
          // 模块就绪，等待有效输入
          ready <= 1;

          if (data_in_valid) begin
            // 单字节消息特殊处理
            if (data_last) begin
              state <= PAD_1;
              ready <= 0;
              fill_pos <= 1;
              msg_length <= 64'd8;
              temp_block[511:504] <= data_in;
            end else begin
              // 正常消息接收
              state <= RECEIVE;
              msg_length <= msg_length + 64'd8;
              temp_block[511-8*byte_count-:8] <= data_in;
              byte_count <= byte_count + 1;
              ready <= (byte_count < 63);
            end
          end else if (data_last) begin
            // 空消息处理
            state <= PAD_1;
            ready <= 0;
            fill_pos <= 0;
            msg_length <= 0;
          end
        end

        // 接收消息状态
        RECEIVE: begin
          if (data_in_valid) begin
            msg_length <= msg_length + 64'd8;
            temp_block[511-8*byte_count-:8] <= data_in;
            byte_count <= byte_count + 1;
            ready <= (byte_count < 63);

            if (byte_count == 63 || data_last) begin
              state <= PAD_1;
              ready <= 0;

              // 计算填充起始位置（考虑块边界）
              fill_pos <= (byte_count == 63) ? 0 : (byte_count + 1);
              // 检查是否需要第二个块放长度
              needs_second_block <= (byte_count >= 55);
            end
          end
        end

        // 添加填充位"1" (0x80)
        PAD_1: begin
          if (fill_pos < 64) begin
            temp_block[511-8*fill_pos-:8] <= 8'h80;
          end

          fill_pos <= fill_pos + 1;
          state <= PAD_0;
        end

        // 处理填充0的状态
        PAD_0: begin
          if (needs_second_block) begin
            // 输出第一个块
            data_out <= temp_block;
            data_out_valid <= 1;

            // 准备第二个块
            temp_block <= 0;
            fill_pos <= 0;
            state <= SECOND_BLOCK;
          end else begin
            // 单块处理
            if (fill_pos < 56) begin
              temp_block[511-8*fill_pos-:8] <= 8'h00;
              fill_pos <= fill_pos + 1;
            end else begin
              state <= PAD_LEN;
            end
          end
        end

        // 处理第二个数据块
        SECOND_BLOCK: begin
          temp_block[511:64] <= 0;
          temp_block[63:0] <= msg_length;

          state <= OUTPUT;
        end

        // 填充消息长度
        PAD_LEN: begin
          temp_block[63:0] <= msg_length;
          state <= OUTPUT;
        end

        // 输出填充完整的数据块，并重置状态
        OUTPUT: begin
          data_out <= temp_block;
          data_out_valid <= 1;

          temp_block <= 0;
          byte_count <= 0;
          fill_pos <= 0;
          state <= IDLE;
        end

        // 未知状态处理
        default: state <= IDLE;
      endcase
    end
  end

endmodule

padding_tb.v
`timescale 1ns / 1ps

module padding_tb ();

  // 时钟和复位信号
  reg clk;
  reg rst_n;

  // 模块输入
  reg [7:0] data_in;
  reg data_in_valid;
  reg data_last;

  // 模块输出
  wire [511:0] data_out;
  wire data_out_valid;
  wire ready;

  // 实例化被测模块
  padding uut (
      .clk(clk),
      .rst_n(rst_n),
      .data_in(data_in),
      .data_in_valid(data_in_valid),
      .data_last(data_last),
      .data_out(data_out),
      .data_out_valid(data_out_valid),
      .ready(ready)
  );

  // 时钟生成（周期10ns）
  initial begin
    clk = 0;
    forever #5 clk = ~clk;
  end

  // 测试过程
  initial begin
    // =============================================
    // 测试用例1：正常消息"abc"测试
    // =============================================
    $display("\n[TEST CASE 1] Testing normal message 'abc'");

    // 初始化
    #20;
    rst_n = 0;
    data_in = 0;
    data_in_valid = 0;
    data_last = 0;
    #10;

    // 释放复位
    rst_n = 1;
    #10;

    // 等待模块就绪
    wait (ready);
    @(posedge clk);

    // 发送消息序列
    // 消息"a"
    data_in = "a";
    data_in_valid = 1;
    data_last = 0;
    @(posedge clk);

    // 消息"b"
    data_in = "b";
    @(posedge clk);

    // 消息"c"（最后一个字节）
    data_in   = "c";
    data_last = 1;
    @(posedge clk);

    // 结束输入
    data_in_valid = 0;
    data_last  = 0;

    // 等待填充完成
    wait (data_out_valid);

    // 显示结果
    $display("\nPadded block (hexadecimal):");
    $display("%h %h %h %h", data_out[511:480], data_out[479:448], data_out[447:416], data_out[415:384]);
    $display("%h %h %h %h", data_out[383:352], data_out[351:320], data_out[319:288], data_out[287:256]);
    $display("%h %h %h %h", data_out[255:224], data_out[223:192], data_out[191:160], data_out[159:128]);
    $display("%h %h %h %h", data_out[127:96], data_out[95:64], data_out[63:32], data_out[31:0]);

    // 验证结果
    if (data_out === 512'h61626380000000000000000000000000000000000000000000000000000000000000000000000000000000000000000000000000000000000000000000000018) begin
      $display("[RESULT] PASS: Output matches expected pattern");
    end else begin
      $display("[RESULT] FAIL: Output mismatch");
      $display("Expected: 6162638000000000...00000018");
      $display("Received: %h", data_out);
    end

    // =============================================
    // 测试用例2：空消息测试
    // =============================================
    $display("\n[TEST CASE 2] Testing empty message");

    // 重新初始化
    #20;
    rst_n = 0;
    data_in = 0;
    data_in_valid = 0;
    data_last = 0;
    #10;

    // 释放复位
    rst_n = 1;
    #10;

    // 等待模块就绪
    wait (ready);
    @(posedge clk);

    // 发送空消息（仅last信号）
    data_in_valid = 0;
    data_last  = 1;
    @(posedge clk);
    data_last = 0;

    // 等待填充完成
    wait (data_out_valid);

    // 显示结果
    $display("\nPadded block (hexadecimal):");
    $display("%h %h %h %h", data_out[511:480], data_out[479:448], data_out[447:416], data_out[415:384]);
    $display("%h %h %h %h", data_out[383:352], data_out[351:320], data_out[319:288], data_out[287:256]);
    $display("%h %h %h %h", data_out[255:224], data_out[223:192], data_out[191:160], data_out[159:128]);
    $display("%h %h %h %h", data_out[127:96], data_out[95:64], data_out[63:32], data_out[31:0]);

    // 验证结果
    if (data_out === 512'h80000000000000000000000000000000000000000000000000000000000000000000000000000000000000000000000000000000000000000000000000000000) begin
      $display("[RESULT] PASS: Empty message padded correctly");
    end else begin
      $display("[RESULT] FAIL: Empty message padding error");
      $display("Expected: 80000000...00000000");
      $display("Received: %h", data_out);
    end

    // =============================================
    // 测试用例3：单字节消息测试
    // =============================================
    $display("\n[TEST CASE 3] Testing single byte message 'A'");

    // 重新初始化
    #20;
    rst_n = 0;
    data_in = 0;
    data_in_valid = 0;
    data_last = 0;
    #10;

    // 释放复位
    rst_n = 1;
    #10;

    // 等待模块就绪
    wait (ready);
    @(posedge clk);

    // 发送单字节消息 "A"
    data_in = "A";
    data_in_valid = 1;
    data_last = 1;  // 标记为最后一个字节
    @(posedge clk);

    // 结束输入
    data_in_valid = 0;
    data_last  = 0;

    // 等待填充完成
    wait (data_out_valid);

    // 显示结果
    $display("\nPadded block (hexadecimal):");
    $display("%h %h %h %h", data_out[511:480], data_out[479:448], data_out[447:416], data_out[415:384]);
    $display("%h %h %h %h", data_out[383:352], data_out[351:320], data_out[319:288], data_out[287:256]);
    $display("%h %h %h %h", data_out[255:224], data_out[223:192], data_out[191:160], data_out[159:128]);
    $display("%h %h %h %h", data_out[127:96], data_out[95:64], data_out[63:32], data_out[31:0]);

    // 验证结果 (单字节'A'=0x41, 长度8位)
    // 格式: 41 80 00...00 00000008
    if (data_out === 512'h41800000000000000000000000000000000000000000000000000000000000000000000000000000000000000000000000000000000000000000000000000008) begin  // 长度字段 (8位)
      $display("[RESULT] PASS: Single byte message padded correctly");
    end else begin
      $display("[RESULT] FAIL: Single byte message padding error");
      $display("Expected: 41800000...00000008");
      $display("Received: %h", data_out);
      $display("Message byte: %h", data_out[511:504]);
      $display("Length field: %h", data_out[63:0]);
    end

    // =============================================
    // 测试用例4：55字节消息测试 (正好填充一个块)
    // =============================================
    $display("\n[TEST CASE 4] Testing 55-byte message");

    // 重新初始化
    #20;
    rst_n = 0;
    data_in = 0;
    data_in_valid = 0;
    data_last = 0;
    #10;

    // 释放复位
    rst_n = 1;
    #10;

    // 等待模块就绪
    wait (ready);
    @(posedge clk);

    // 发送55字节消息 (全部发送0xAA作为测试数据)
    for (integer i = 0; i < 55; i = i + 1) begin
      data_in = 8'hAA;  // 测试数据
      data_in_valid = 1;
      data_last = (i == 54);  // 最后一个字节设置msg_last
      @(posedge clk);
    end

    // 结束输入
    data_in_valid = 0;
    data_last  = 0;

    // 等待填充完成
    wait (data_out_valid);

    // 显示填充结果
    $display("\nPadded block (hexadecimal):");
    $display("%h %h %h %h", data_out[511:480], data_out[479:448], data_out[447:416], data_out[415:384]);
    $display("%h %h %h %h", data_out[383:352], data_out[351:320], data_out[319:288], data_out[287:256]);
    $display("%h %h %h %h", data_out[255:224], data_out[223:192], data_out[191:160], data_out[159:128]);
    $display("%h %h %h %h", data_out[127:96], data_out[95:64], data_out[63:32], data_out[31:0]);

    // 验证结果
    // 格式: 预期格式：55个AA + 80 + 7个00 + 64位长度(0x00000000000001B8)
    if (data_out === 512'haaaaaaaaaaaaaaaaaaaaaaaaaaaaaaaaaaaaaaaaaaaaaaaaaaaaaaaaaaaaaaaaaaaaaaaaaaaaaaaaaaaaaaaaaaaaaaaaaaaaaaaaaaaaaa8000000000000001b8) begin  // 长度字段 (8位)
      $display("[RESULT] PASS: 55-byte message padded correctly in one block");
    end else begin
      $display("[RESULT] FAIL: Padding error");
      $display("Expected: 55*AA + 80 + 7*00 + 00000000000001B8");
      $display("Received: %h", data_out);
    end

    // =============================================
    // 测试用例5：56字节消息测试 (需要两个块)
    // =============================================
    $display("\n[TEST CASE 5] Testing 56-byte message");

    // 重新初始化
    #20;
    rst_n = 0;
    data_in = 0;
    data_in_valid = 0;
    data_last = 0;
    #10;

    // 释放复位
    rst_n = 1;
    #10;

    // 等待模块就绪
    wait (ready);
    @(posedge clk);

    // 发送56字节消息 (全部发送0xBB作为测试数据)
    for (integer i = 0; i < 56; i = i + 1) begin
      data_in = 8'hBB;  // 测试数据
      data_in_valid = 1;
      data_last = (i == 55);  // 最后一个字节设置msg_last
      @(posedge clk);
    end

    // 结束输入
    data_in_valid = 0;
    data_last  = 0;

    // 等待第一个填充块完成
    wait (data_out_valid);

    // 显示第一个填充块
    $display("\nFirst padded block (hexadecimal):");
    $display("%h %h %h %h", data_out[511:480], data_out[479:448], data_out[447:416], data_out[415:384]);
    $display("%h %h %h %h", data_out[383:352], data_out[351:320], data_out[319:288], data_out[287:256]);
    $display("%h %h %h %h", data_out[255:224], data_out[223:192], data_out[191:160], data_out[159:128]);
    $display("%h %h %h %h", data_out[127:96], data_out[95:64], data_out[63:32], data_out[31:0]);

    // 验证第一个块
    // 预期格式：56个BB + 80 + 7个00
    if (data_out === 512'hbbbbbbbbbbbbbbbbbbbbbbbbbbbbbbbbbbbbbbbbbbbbbbbbbbbbbbbbbbbbbbbbbbbbbbbbbbbbbbbbbbbbbbbbbbbbbbbbbbbbbbbbbbbbbbbb8000000000000000) begin
      $display("[RESULT] PASS: First block of 56-byte message padded correctly");
    end else begin
      $display("[RESULT] FAIL: First block padding error");
      $display("Expected: 56*BB + 80 + 7*00");
      $display("Received: %h", data_out);
    end

    // 等待第一个块的valid信号变低
    @(negedge data_out_valid);
    // 等待第二个填充块完成
    wait (data_out_valid);

    // 显示第二个填充块
    $display("\nSecond padded block (hexadecimal):");
    $display("%h %h %h %h", data_out[511:480], data_out[479:448], data_out[447:416], data_out[415:384]);
    $display("%h %h %h %h", data_out[383:352], data_out[351:320], data_out[319:288], data_out[287:256]);
    $display("%h %h %h %h", data_out[255:224], data_out[223:192], data_out[191:160], data_out[159:128]);
    $display("%h %h %h %h", data_out[127:96], data_out[95:64], data_out[63:32], data_out[31:0]);

    // 验证第二个块
    // 预期格式：448位0 + 64位长度(0x00000000000001C0)    
    if (data_out === 512'h000000000000000000000000000000000000000000000000000000000000000000000000000000000000000000000000000000000000000000000000000001c0) begin
      $display("[RESULT] PASS: Second block of 56-byte message padded correctly");
    end else begin
      $display("[RESULT] FAIL: Second block padding error");
      $display("Expected: all zeros + 00000000000001C0");
      $display("Received: %h", data_out);
    end

    // =============================================
    // 结束仿真
    // =============================================
    #100;
    $display("\n[SIMULATION FINISHED]");
    $finish;
  end

  // 波形转储
  initial begin
    $dumpfile("padding.vcd");
    $dumpvars(0, padding_tb);
  end

endmodule

padding.vcd
$date
	Sun Jul 27 15:57:14 2025
$end
$version
	Icarus Verilog
$end
$timescale
	1ps
$end
$scope module padding_tb $end
$var wire 1 ! ready $end
$var wire 1 " data_out_valid $end
$var wire 512 # data_out [511:0] $end
$var reg 1 $ clk $end
$var reg 8 % data_in [7:0] $end
$var reg 1 & data_in_valid $end
$var reg 1 ' data_last $end
$var reg 1 ( rst_n $end
$scope module uut $end
$var wire 1 $ clk $end
$var wire 8 ) data_in [7:0] $end
$var wire 1 & data_in_valid $end
$var wire 1 ' data_last $end
$var wire 1 ( rst_n $end
$var parameter 3 * IDLE $end
$var parameter 3 + OUTPUT $end
$var parameter 3 , PAD_0 $end
$var parameter 3 - PAD_1 $end
$var parameter 3 . PAD_LEN $end
$var parameter 3 / RECEIVE $end
$var parameter 3 0 SECOND_BLOCK $end
$var reg 6 1 byte_count [5:0] $end
$var reg 512 2 data_out [511:0] $end
$var reg 1 " data_out_valid $end
$var reg 6 3 fill_pos [5:0] $end
$var reg 64 4 msg_length [63:0] $end
$var reg 1 5 needs_second_block $end
$var reg 1 ! ready $end
$var reg 3 6 state [2:0] $end
$var reg 512 7 temp_block [511:0] $end
$upscope $end
$scope begin $ivl_for_loop0 $end
$var integer 32 8 i [31:0] $end
$upscope $end
$scope begin $ivl_for_loop1 $end
$var integer 32 9 i [31:0] $end
$upscope $end
$upscope $end
$enddefinitions $end
$comment Show the parameter values. $end
$dumpall
b110 0
b1 /
b100 .
b10 -
b11 ,
b101 +
b0 *
$end
#0
$dumpvars
bx 9
bx 8
bx 7
bx 6
x5
bx 4
bx 3
bx 2
bx 1
bx )
x(
x'
x&
bx %
0$
bx #
x"
x!
$end
#5000
b0 6
0"
1$
#10000
0$
#15000
1!
1$
#20000
05
b0 3
0!
b0 #
b0 2
b0 7
b0 1
b0 4
0$
0'
0&
b0 %
b0 )
0(
#25000
1$
#30000
0$
1(
#35000
1!
1$
#40000
0$
#45000
b1 1
b1100001000000000000000000000000000000000000000000000000000000000000000000000000000000000000000000000000000000000000000000000000000000000000000000000000000000000000000000000000000000000000000000000000000000000000000000000000000000000000000000000000000000000000000000000000000000000000000000000000000000000000000000000000000000000000000000000000000000000000000000000000000000000000000000000000000000000000000000000000000000000000000000000000000000000000000000000000000000000000000000000000000000000000000000000000 7
b1000 4
b1 6
1&
b1100001 %
b1100001 )
1$
#50000
0$
#55000
b10 1
b1100001011000100000000000000000000000000000000000000000000000000000000000000000000000000000000000000000000000000000000000000000000000000000000000000000000000000000000000000000000000000000000000000000000000000000000000000000000000000000000000000000000000000000000000000000000000000000000000000000000000000000000000000000000000000000000000000000000000000000000000000000000000000000000000000000000000000000000000000000000000000000000000000000000000000000000000000000000000000000000000000000000000000000000000000000 7
b10000 4
b1100010 %
b1100010 )
1$
#60000
0$
#65000
b11 3
0!
b10 6
b11 1
b1100001011000100110001100000000000000000000000000000000000000000000000000000000000000000000000000000000000000000000000000000000000000000000000000000000000000000000000000000000000000000000000000000000000000000000000000000000000000000000000000000000000000000000000000000000000000000000000000000000000000000000000000000000000000000000000000000000000000000000000000000000000000000000000000000000000000000000000000000000000000000000000000000000000000000000000000000000000000000000000000000000000000000000000000000000 7
b11000 4
1'
b1100011 %
b1100011 )
1$
#70000
0$
#75000
b11 6
b100 3
b1100001011000100110001110000000000000000000000000000000000000000000000000000000000000000000000000000000000000000000000000000000000000000000000000000000000000000000000000000000000000000000000000000000000000000000000000000000000000000000000000000000000000000000000000000000000000000000000000000000000000000000000000000000000000000000000000000000000000000000000000000000000000000000000000000000000000000000000000000000000000000000000000000000000000000000000000000000000000000000000000000000000000000000000000000000 7
0'
0&
1$
#80000
0$
#85000
b101 3
1$
#90000
0$
#95000
b110 3
1$
#100000
0$
#105000
b111 3
1$
#110000
0$
#115000
b1000 3
1$
#120000
0$
#125000
b1001 3
1$
#130000
0$
#135000
b1010 3
1$
#140000
0$
#145000
b1011 3
1$
#150000
0$
#155000
b1100 3
1$
#160000
0$
#165000
b1101 3
1$
#170000
0$
#175000
b1110 3
1$
#180000
0$
#185000
b1111 3
1$
#190000
0$
#195000
b10000 3
1$
#200000
0$
#205000
b10001 3
1$
#210000
0$
#215000
b10010 3
1$
#220000
0$
#225000
b10011 3
1$
#230000
0$
#235000
b10100 3
1$
#240000
0$
#245000
b10101 3
1$
#250000
0$
#255000
b10110 3
1$
#260000
0$
#265000
b10111 3
1$
#270000
0$
#275000
b11000 3
1$
#280000
0$
#285000
b11001 3
1$
#290000
0$
#295000
b11010 3
1$
#300000
0$
#305000
b11011 3
1$
#310000
0$
#315000
b11100 3
1$
#320000
0$
#325000
b11101 3
1$
#330000
0$
#335000
b11110 3
1$
#340000
0$
#345000
b11111 3
1$
#350000
0$
#355000
b100000 3
1$
#360000
0$
#365000
b100001 3
1$
#370000
0$
#375000
b100010 3
1$
#380000
0$
#385000
b100011 3
1$
#390000
0$
#395000
b100100 3
1$
#400000
0$
#405000
b100101 3
1$
#410000
0$
#415000
b100110 3
1$
#420000
0$
#425000
b100111 3
1$
#430000
0$
#435000
b101000 3
1$
#440000
0$
#445000
b101001 3
1$
#450000
0$
#455000
b101010 3
1$
#460000
0$
#465000
b101011 3
1$
#470000
0$
#475000
b101100 3
1$
#480000
0$
#485000
b101101 3
1$
#490000
0$
#495000
b101110 3
1$
#500000
0$
#505000
b101111 3
1$
#510000
0$
#515000
b110000 3
1$
#520000
0$
#525000
b110001 3
1$
#530000
0$
#535000
b110010 3
1$
#540000
0$
#545000
b110011 3
1$
#550000
0$
#555000
b110100 3
1$
#560000
0$
#565000
b110101 3
1$
#570000
0$
#575000
b110110 3
1$
#580000
0$
#585000
b110111 3
1$
#590000
0$
#595000
b111000 3
1$
#600000
0$
#605000
b100 6
1$
#610000
0$
#615000
b101 6
b1100001011000100110001110000000000000000000000000000000000000000000000000000000000000000000000000000000000000000000000000000000000000000000000000000000000000000000000000000000000000000000000000000000000000000000000000000000000000000000000000000000000000000000000000000000000000000000000000000000000000000000000000000000000000000000000000000000000000000000000000000000000000000000000000000000000000000000000000000000000000000000000000000000000000000000000000000000000000000000000000000000000000000000000000011000 7
1$
#620000
0$
#625000
b0 6
b0 3
b0 1
b0 7
1"
b1100001011000100110001110000000000000000000000000000000000000000000000000000000000000000000000000000000000000000000000000000000000000000000000000000000000000000000000000000000000000000000000000000000000000000000000000000000000000000000000000000000000000000000000000000000000000000000000000000000000000000000000000000000000000000000000000000000000000000000000000000000000000000000000000000000000000000000000000000000000000000000000000000000000000000000000000000000000000000000000000000000000000000000000000011000 #
b1100001011000100110001110000000000000000000000000000000000000000000000000000000000000000000000000000000000000000000000000000000000000000000000000000000000000000000000000000000000000000000000000000000000000000000000000000000000000000000000000000000000000000000000000000000000000000000000000000000000000000000000000000000000000000000000000000000000000000000000000000000000000000000000000000000000000000000000000000000000000000000000000000000000000000000000000000000000000000000000000000000000000000000000000011000 2
1$
#630000
0$
#635000
1!
0"
1$
#640000
0$
#645000
0!
b0 #
b0 2
b0 4
1$
b0 %
b0 )
0(
#650000
0$
#655000
1!
1$
1(
#660000
0$
#665000
0!
b10 6
1'
1$
#670000
0$
#675000
b11 6
b1 3
b10000000000000000000000000000000000000000000000000000000000000000000000000000000000000000000000000000000000000000000000000000000000000000000000000000000000000000000000000000000000000000000000000000000000000000000000000000000000000000000000000000000000000000000000000000000000000000000000000000000000000000000000000000000000000000000000000000000000000000000000000000000000000000000000000000000000000000000000000000000000000000000000000000000000000000000000000000000000000000000000000000000000000000000000000000000 7
0'
1$
#680000
0$
#685000
b10 3
1$
#690000
0$
#695000
b11 3
1$
#700000
0$
#705000
b100 3
1$
#710000
0$
#715000
b101 3
1$
#720000
0$
#725000
b110 3
1$
#730000
0$
#735000
b111 3
1$
#740000
0$
#745000
b1000 3
1$
#750000
0$
#755000
b1001 3
1$
#760000
0$
#765000
b1010 3
1$
#770000
0$
#775000
b1011 3
1$
#780000
0$
#785000
b1100 3
1$
#790000
0$
#795000
b1101 3
1$
#800000
0$
#805000
b1110 3
1$
#810000
0$
#815000
b1111 3
1$
#820000
0$
#825000
b10000 3
1$
#830000
0$
#835000
b10001 3
1$
#840000
0$
#845000
b10010 3
1$
#850000
0$
#855000
b10011 3
1$
#860000
0$
#865000
b10100 3
1$
#870000
0$
#875000
b10101 3
1$
#880000
0$
#885000
b10110 3
1$
#890000
0$
#895000
b10111 3
1$
#900000
0$
#905000
b11000 3
1$
#910000
0$
#915000
b11001 3
1$
#920000
0$
#925000
b11010 3
1$
#930000
0$
#935000
b11011 3
1$
#940000
0$
#945000
b11100 3
1$
#950000
0$
#955000
b11101 3
1$
#960000
0$
#965000
b11110 3
1$
#970000
0$
#975000
b11111 3
1$
#980000
0$
#985000
b100000 3
1$
#990000
0$
#995000
b100001 3
1$
#1000000
0$
#1005000
b100010 3
1$
#1010000
0$
#1015000
b100011 3
1$
#1020000
0$
#1025000
b100100 3
1$
#1030000
0$
#1035000
b100101 3
1$
#1040000
0$
#1045000
b100110 3
1$
#1050000
0$
#1055000
b100111 3
1$
#1060000
0$
#1065000
b101000 3
1$
#1070000
0$
#1075000
b101001 3
1$
#1080000
0$
#1085000
b101010 3
1$
#1090000
0$
#1095000
b101011 3
1$
#1100000
0$
#1105000
b101100 3
1$
#1110000
0$
#1115000
b101101 3
1$
#1120000
0$
#1125000
b101110 3
1$
#1130000
0$
#1135000
b101111 3
1$
#1140000
0$
#1145000
b110000 3
1$
#1150000
0$
#1155000
b110001 3
1$
#1160000
0$
#1165000
b110010 3
1$
#1170000
0$
#1175000
b110011 3
1$
#1180000
0$
#1185000
b110100 3
1$
#1190000
0$
#1195000
b110101 3
1$
#1200000
0$
#1205000
b110110 3
1$
#1210000
0$
#1215000
b110111 3
1$
#1220000
0$
#1225000
b111000 3
1$
#1230000
0$
#1235000
b100 6
1$
#1240000
0$
#1245000
b101 6
1$
#1250000
0$
#1255000
b0 6
b0 3
b0 7
1"
b10000000000000000000000000000000000000000000000000000000000000000000000000000000000000000000000000000000000000000000000000000000000000000000000000000000000000000000000000000000000000000000000000000000000000000000000000000000000000000000000000000000000000000000000000000000000000000000000000000000000000000000000000000000000000000000000000000000000000000000000000000000000000000000000000000000000000000000000000000000000000000000000000000000000000000000000000000000000000000000000000000000000000000000000000000000 #
b10000000000000000000000000000000000000000000000000000000000000000000000000000000000000000000000000000000000000000000000000000000000000000000000000000000000000000000000000000000000000000000000000000000000000000000000000000000000000000000000000000000000000000000000000000000000000000000000000000000000000000000000000000000000000000000000000000000000000000000000000000000000000000000000000000000000000000000000000000000000000000000000000000000000000000000000000000000000000000000000000000000000000000000000000000000 2
1$
#1260000
0$
#1265000
1!
0"
1$
#1270000
0$
#1275000
0!
b0 #
b0 2
1$
0(
#1280000
0$
#1285000
1!
1$
1(
#1290000
0$
#1295000
b1000001000000000000000000000000000000000000000000000000000000000000000000000000000000000000000000000000000000000000000000000000000000000000000000000000000000000000000000000000000000000000000000000000000000000000000000000000000000000000000000000000000000000000000000000000000000000000000000000000000000000000000000000000000000000000000000000000000000000000000000000000000000000000000000000000000000000000000000000000000000000000000000000000000000000000000000000000000000000000000000000000000000000000000000000000 7
b1000 4
b1 3
0!
b10 6
1'
1&
b1000001 %
b1000001 )
1$
#1300000
0$
#1305000
b11 6
b10 3
b1000001100000000000000000000000000000000000000000000000000000000000000000000000000000000000000000000000000000000000000000000000000000000000000000000000000000000000000000000000000000000000000000000000000000000000000000000000000000000000000000000000000000000000000000000000000000000000000000000000000000000000000000000000000000000000000000000000000000000000000000000000000000000000000000000000000000000000000000000000000000000000000000000000000000000000000000000000000000000000000000000000000000000000000000000000 7
0'
0&
1$
#1310000
0$
#1315000
b11 3
1$
#1320000
0$
#1325000
b100 3
1$
#1330000
0$
#1335000
b101 3
1$
#1340000
0$
#1345000
b110 3
1$
#1350000
0$
#1355000
b111 3
1$
#1360000
0$
#1365000
b1000 3
1$
#1370000
0$
#1375000
b1001 3
1$
#1380000
0$
#1385000
b1010 3
1$
#1390000
0$
#1395000
b1011 3
1$
#1400000
0$
#1405000
b1100 3
1$
#1410000
0$
#1415000
b1101 3
1$
#1420000
0$
#1425000
b1110 3
1$
#1430000
0$
#1435000
b1111 3
1$
#1440000
0$
#1445000
b10000 3
1$
#1450000
0$
#1455000
b10001 3
1$
#1460000
0$
#1465000
b10010 3
1$
#1470000
0$
#1475000
b10011 3
1$
#1480000
0$
#1485000
b10100 3
1$
#1490000
0$
#1495000
b10101 3
1$
#1500000
0$
#1505000
b10110 3
1$
#1510000
0$
#1515000
b10111 3
1$
#1520000
0$
#1525000
b11000 3
1$
#1530000
0$
#1535000
b11001 3
1$
#1540000
0$
#1545000
b11010 3
1$
#1550000
0$
#1555000
b11011 3
1$
#1560000
0$
#1565000
b11100 3
1$
#1570000
0$
#1575000
b11101 3
1$
#1580000
0$
#1585000
b11110 3
1$
#1590000
0$
#1595000
b11111 3
1$
#1600000
0$
#1605000
b100000 3
1$
#1610000
0$
#1615000
b100001 3
1$
#1620000
0$
#1625000
b100010 3
1$
#1630000
0$
#1635000
b100011 3
1$
#1640000
0$
#1645000
b100100 3
1$
#1650000
0$
#1655000
b100101 3
1$
#1660000
0$
#1665000
b100110 3
1$
#1670000
0$
#1675000
b100111 3
1$
#1680000
0$
#1685000
b101000 3
1$
#1690000
0$
#1695000
b101001 3
1$
#1700000
0$
#1705000
b101010 3
1$
#1710000
0$
#1715000
b101011 3
1$
#1720000
0$
#1725000
b101100 3
1$
#1730000
0$
#1735000
b101101 3
1$
#1740000
0$
#1745000
b101110 3
1$
#1750000
0$
#1755000
b101111 3
1$
#1760000
0$
#1765000
b110000 3
1$
#1770000
0$
#1775000
b110001 3
1$
#1780000
0$
#1785000
b110010 3
1$
#1790000
0$
#1795000
b110011 3
1$
#1800000
0$
#1805000
b110100 3
1$
#1810000
0$
#1815000
b110101 3
1$
#1820000
0$
#1825000
b110110 3
1$
#1830000
0$
#1835000
b110111 3
1$
#1840000
0$
#1845000
b111000 3
1$
#1850000
0$
#1855000
b100 6
1$
#1860000
0$
#1865000
b101 6
b1000001100000000000000000000000000000000000000000000000000000000000000000000000000000000000000000000000000000000000000000000000000000000000000000000000000000000000000000000000000000000000000000000000000000000000000000000000000000000000000000000000000000000000000000000000000000000000000000000000000000000000000000000000000000000000000000000000000000000000000000000000000000000000000000000000000000000000000000000000000000000000000000000000000000000000000000000000000000000000000000000000000000000000000000001000 7
1$
#1870000
0$
#1875000
b0 6
b0 3
b0 7
1"
b1000001100000000000000000000000000000000000000000000000000000000000000000000000000000000000000000000000000000000000000000000000000000000000000000000000000000000000000000000000000000000000000000000000000000000000000000000000000000000000000000000000000000000000000000000000000000000000000000000000000000000000000000000000000000000000000000000000000000000000000000000000000000000000000000000000000000000000000000000000000000000000000000000000000000000000000000000000000000000000000000000000000000000000000000001000 #
b1000001100000000000000000000000000000000000000000000000000000000000000000000000000000000000000000000000000000000000000000000000000000000000000000000000000000000000000000000000000000000000000000000000000000000000000000000000000000000000000000000000000000000000000000000000000000000000000000000000000000000000000000000000000000000000000000000000000000000000000000000000000000000000000000000000000000000000000000000000000000000000000000000000000000000000000000000000000000000000000000000000000000000000000000001000 2
1$
#1880000
0$
#1885000
1!
0"
1$
#1890000
0$
#1895000
0!
b0 #
b0 2
b0 4
1$
b0 %
b0 )
0(
#1900000
0$
#1905000
1!
1$
1(
#1910000
0$
#1915000
b1 1
b10101010000000000000000000000000000000000000000000000000000000000000000000000000000000000000000000000000000000000000000000000000000000000000000000000000000000000000000000000000000000000000000000000000000000000000000000000000000000000000000000000000000000000000000000000000000000000000000000000000000000000000000000000000000000000000000000000000000000000000000000000000000000000000000000000000000000000000000000000000000000000000000000000000000000000000000000000000000000000000000000000000000000000000000000000000 7
b1000 4
b1 6
1&
b10101010 %
b10101010 )
b0 8
1$
#1920000
0$
